[
  {
    "Type": "Function",
    "Name": "ExecuteUbergraph_BP_Danmaku_BossAida_Skill1301",
    "Outer": "BP_Danmaku_BossAida_Skill1301_C",
    "Class": "UScriptClass'Function'",
    "Flags": "RF_Public | RF_WasLoaded | RF_LoadCompleted",
    "ChildProperties": [
      {
        "Type": "IntProperty",
        "Name": "EntryPoint",
        "Flags": "RF_Public",
        "ElementSize": 4,
        "PropertyFlags": "BlueprintVisible | BlueprintReadOnly | Parm"
      },
      {
        "Type": "IntProperty",
        "Name": "___int_Array_Index_Variable",
        "Flags": "RF_Public",
        "ElementSize": 4
      },
      {
        "Type": "IntProperty",
        "Name": "___int_Loop_Counter_Variable",
        "Flags": "RF_Public",
        "ElementSize": 4
      },
      {
        "Type": "IntProperty",
        "Name": "CallFunc_Add_IntInt_ReturnValue",
        "Flags": "RF_Public",
        "ElementSize": 4
      },
      {
        "Type": "ArrayProperty",
        "Name": "CallFunc_Map_Values_Values",
        "Flags": "RF_Public",
        "ElementSize": 16,
        "PropertyFlags": "ReferenceParm | ContainsInstancedReference",
        "Inner": {
          "Type": "ObjectProperty",
          "Name": "CallFunc_Map_Values_Values",
          "Flags": "RF_Public",
          "ElementSize": 8,
          "PropertyFlags": "InstancedReference",
          "PropertyClass": {
            "ObjectName": "Class'DanmakuLaunchPort'",
            "ObjectPath": "/Script/EM"
          }
        }
      },
      {
        "Type": "IntProperty",
        "Name": "CallFunc_Array_Length_ReturnValue",
        "Flags": "RF_Public",
        "ElementSize": 4
      },
      {
        "Type": "ObjectProperty",
        "Name": "CallFunc_Array_Get_Item",
        "Flags": "RF_Public",
        "ElementSize": 8,
        "PropertyFlags": "InstancedReference",
        "PropertyClass": {
          "ObjectName": "Class'DanmakuLaunchPort'",
          "ObjectPath": "/Script/EM"
        }
      },
      {
        "Type": "BoolProperty",
        "Name": "CallFunc_Less_IntInt_ReturnValue",
        "Flags": "RF_Public",
        "ElementSize": 1,
        "FieldSize": 1,
        "ByteOffset": 0,
        "ByteMask": 1,
        "FieldMask": 255,
        "BoolSize": 1,
        "bIsNativeBool": true
      }
    ],
    "FunctionFlags": "FUNC_Final | FUNC_UbergraphFunction | FUNC_HasDefaults"
  },
  {
    "Type": "Function",
    "Name": "DanmakuFire",
    "Outer": "BP_Danmaku_BossAida_Skill1301_C",
    "Class": "UScriptClass'Function'",
    "Flags": "RF_Public | RF_WasLoaded | RF_LoadCompleted",
    "SuperStruct": {
      "ObjectName": "Function'DanmakuTemplate:DanmakuFire'",
      "ObjectPath": "/Script/EM"
    },
    "FunctionFlags": "FUNC_Event | FUNC_Public | FUNC_BlueprintEvent"
  },
  {
    "Type": "BlueprintGeneratedClass",
    "Name": "BP_Danmaku_BossAida_Skill1301_C",
    "Class": "UScriptClass'BlueprintGeneratedClass'",
    "Super": {
      "ObjectName": "BlueprintGeneratedClass'BP_DanmakuTemplate_C'",
      "ObjectPath": "EM/Content/BluePrints/Combat/Danmaku/BP_DanmakuTemplate.6"
    },
    "Flags": "RF_Public | RF_Transactional | RF_WasLoaded | RF_LoadCompleted",
    "Properties": {
      "SimpleConstructionScript": {
        "ObjectName": "SimpleConstructionScript'BP_Danmaku_BossAida_Skill1301_C:SimpleConstructionScript_0'",
        "ObjectPath": "EM/Content/BluePrints/Combat/Danmaku/BP_Danmakus/BP_Danmaku_BossAida_Skill1301.25"
      },
      "InheritableComponentHandler": {
        "ObjectName": "InheritableComponentHandler'BP_Danmaku_BossAida_Skill1301_C:InheritableComponentHandler'",
        "ObjectPath": "EM/Content/BluePrints/Combat/Danmaku/BP_Danmakus/BP_Danmaku_BossAida_Skill1301.13"
      },
      "UberGraphFunction": {
        "ObjectName": "Function'BP_Danmaku_BossAida_Skill1301_C:ExecuteUbergraph_BP_Danmaku_BossAida_Skill1301'",
        "ObjectPath": "EM/Content/BluePrints/Combat/Danmaku/BP_Danmakus/BP_Danmaku_BossAida_Skill1301.0"
      }
    },
    "SuperStruct": {
      "ObjectName": "BlueprintGeneratedClass'BP_DanmakuTemplate_C'",
      "ObjectPath": "EM/Content/BluePrints/Combat/Danmaku/BP_DanmakuTemplate.6"
    },
    "Children": [
      {
        "ObjectName": "Function'BP_Danmaku_BossAida_Skill1301_C:DanmakuFire'",
        "ObjectPath": "EM/Content/BluePrints/Combat/Danmaku/BP_Danmakus/BP_Danmaku_BossAida_Skill1301.1"
      },
      {
        "ObjectName": "Function'BP_Danmaku_BossAida_Skill1301_C:ExecuteUbergraph_BP_Danmaku_BossAida_Skill1301'",
        "ObjectPath": "EM/Content/BluePrints/Combat/Danmaku/BP_Danmakus/BP_Danmaku_BossAida_Skill1301.0"
      }
    ],
    "ChildProperties": [
      {
        "Type": "StructProperty",
        "Name": "UberGraphFrame",
        "Flags": "RF_Public | RF_LoadCompleted",
        "ElementSize": 16,
        "PropertyFlags": "Transient | DuplicateTransient",
        "Struct": {
          "ObjectName": "ScriptStruct'PointerToUberGraphFrame'",
          "ObjectPath": "/Script/Engine"
        }
      },
      {
        "Type": "ObjectProperty",
        "Name": "BP_DanmakuLaunchPort7",
        "Flags": "RF_Public | RF_LoadCompleted",
        "ElementSize": 8,
        "PropertyFlags": "BlueprintVisible | InstancedReference | NonTransactional",
        "PropertyClass": {
          "ObjectName": "BlueprintGeneratedClass'BP_DanmakuLaunchPort_C'",
          "ObjectPath": "EM/Content/BluePrints/Combat/Danmaku/BP_DanmakuLaunchPort.1"
        }
      },
      {
        "Type": "ObjectProperty",
        "Name": "BP_DanmakuLaunchPort6",
        "Flags": "RF_Public | RF_LoadCompleted",
        "ElementSize": 8,
        "PropertyFlags": "BlueprintVisible | InstancedReference | NonTransactional",
        "PropertyClass": {
          "ObjectName": "BlueprintGeneratedClass'BP_DanmakuLaunchPort_C'",
          "ObjectPath": "EM/Content/BluePrints/Combat/Danmaku/BP_DanmakuLaunchPort.1"
        }
      },
      {
        "Type": "ObjectProperty",
        "Name": "BP_DanmakuLaunchPort5",
        "Flags": "RF_Public | RF_LoadCompleted",
        "ElementSize": 8,
        "PropertyFlags": "BlueprintVisible | InstancedReference | NonTransactional",
        "PropertyClass": {
          "ObjectName": "BlueprintGeneratedClass'BP_DanmakuLaunchPort_C'",
          "ObjectPath": "EM/Content/BluePrints/Combat/Danmaku/BP_DanmakuLaunchPort.1"
        }
      },
      {
        "Type": "ObjectProperty",
        "Name": "BP_DanmakuLaunchPort4",
        "Flags": "RF_Public | RF_LoadCompleted",
        "ElementSize": 8,
        "PropertyFlags": "BlueprintVisible | InstancedReference | NonTransactional",
        "PropertyClass": {
          "ObjectName": "BlueprintGeneratedClass'BP_DanmakuLaunchPort_C'",
          "ObjectPath": "EM/Content/BluePrints/Combat/Danmaku/BP_DanmakuLaunchPort.1"
        }
      },
      {
        "Type": "ObjectProperty",
        "Name": "BP_DanmakuLaunchPort3",
        "Flags": "RF_Public | RF_LoadCompleted",
        "ElementSize": 8,
        "PropertyFlags": "BlueprintVisible | InstancedReference | NonTransactional",
        "PropertyClass": {
          "ObjectName": "BlueprintGeneratedClass'BP_DanmakuLaunchPort_C'",
          "ObjectPath": "EM/Content/BluePrints/Combat/Danmaku/BP_DanmakuLaunchPort.1"
        }
      },
      {
        "Type": "ObjectProperty",
        "Name": "BP_DanmakuLaunchPort2",
        "Flags": "RF_Public | RF_LoadCompleted",
        "ElementSize": 8,
        "PropertyFlags": "BlueprintVisible | InstancedReference | NonTransactional",
        "PropertyClass": {
          "ObjectName": "BlueprintGeneratedClass'BP_DanmakuLaunchPort_C'",
          "ObjectPath": "EM/Content/BluePrints/Combat/Danmaku/BP_DanmakuLaunchPort.1"
        }
      },
      {
        "Type": "ObjectProperty",
        "Name": "BP_DanmakuLaunchPort1",
        "Flags": "RF_Public | RF_LoadCompleted",
        "ElementSize": 8,
        "PropertyFlags": "BlueprintVisible | InstancedReference | NonTransactional",
        "PropertyClass": {
          "ObjectName": "BlueprintGeneratedClass'BP_DanmakuLaunchPort_C'",
          "ObjectPath": "EM/Content/BluePrints/Combat/Danmaku/BP_DanmakuLaunchPort.1"
        }
      },
      {
        "Type": "ObjectProperty",
        "Name": "BP_DanmakuLaunchPort",
        "Flags": "RF_Public | RF_LoadCompleted",
        "ElementSize": 8,
        "PropertyFlags": "BlueprintVisible | InstancedReference | NonTransactional",
        "PropertyClass": {
          "ObjectName": "BlueprintGeneratedClass'BP_DanmakuLaunchPort_C'",
          "ObjectPath": "EM/Content/BluePrints/Combat/Danmaku/BP_DanmakuLaunchPort.1"
        }
      }
    ],
    "FuncMap": {
      "ExecuteUbergraph_BP_Danmaku_BossAida_Skill1301": {
        "ObjectName": "Function'BP_Danmaku_BossAida_Skill1301_C:ExecuteUbergraph_BP_Danmaku_BossAida_Skill1301'",
        "ObjectPath": "EM/Content/BluePrints/Combat/Danmaku/BP_Danmakus/BP_Danmaku_BossAida_Skill1301.0"
      },
      "DanmakuFire": {
        "ObjectName": "Function'BP_Danmaku_BossAida_Skill1301_C:DanmakuFire'",
        "ObjectPath": "EM/Content/BluePrints/Combat/Danmaku/BP_Danmakus/BP_Danmaku_BossAida_Skill1301.1"
      }
    },
    "ClassFlags": "CLASS_Config | CLASS_Optional | CLASS_ReplicationDataIsSetUp | CLASS_CompiledFromBlueprint | CLASS_HasInstancedReference",
    "ClassWithin": {
      "ObjectName": "Class'Object'",
      "ObjectPath": "/Script/CoreUObject"
    },
    "ClassConfigName": "Engine",
    "bCooked": true,
    "ClassDefaultObject": {
      "ObjectName": "BP_Danmaku_BossAida_Skill1301_C'Default__BP_Danmaku_BossAida_Skill1301_C'",
      "ObjectPath": "EM/Content/BluePrints/Combat/Danmaku/BP_Danmakus/BP_Danmaku_BossAida_Skill1301.3"
    }
  },
  {
    "Type": "BP_Danmaku_BossAida_Skill1301_C",
    "Name": "Default__BP_Danmaku_BossAida_Skill1301_C",
    "Class": "BlueprintGeneratedClass'EM/Content/BluePrints/Combat/Danmaku/BP_Danmakus/BP_Danmaku_BossAida_Skill1301.BP_Danmaku_BossAida_Skill1301_C'",
    "Template": {
      "ObjectName": "BP_DanmakuTemplate_C'Default__BP_DanmakuTemplate_C'",
      "ObjectPath": "EM/Content/BluePrints/Combat/Danmaku/BP_DanmakuTemplate.7"
    },
    "Flags": "RF_Public | RF_ClassDefaultObject | RF_ArchetypeObject | RF_WasLoaded | RF_LoadCompleted",
    "Properties": {
      "UberGraphFrame": {},
      "Interval": 999.0,
      "DanmakuInstanced": {
        "ObjectName": "DanmakuInstanceComponent'Default__BP_Danmaku_BossAida_Skill1301_C:DanmakuInstanced'",
        "ObjectPath": "EM/Content/BluePrints/Combat/Danmaku/BP_Danmakus/BP_Danmaku_BossAida_Skill1301.12"
      },
      "PortRoot": {
        "ObjectName": "SceneComponent'Default__BP_Danmaku_BossAida_Skill1301_C:PortRoot'",
        "ObjectPath": "EM/Content/BluePrints/Combat/Danmaku/BP_Danmakus/BP_Danmaku_BossAida_Skill1301.15"
      },
      "RootComponent": {
        "ObjectName": "DanmakuInstanceComponent'Default__BP_Danmaku_BossAida_Skill1301_C:DanmakuInstanced'",
        "ObjectPath": "EM/Content/BluePrints/Combat/Danmaku/BP_Danmakus/BP_Danmaku_BossAida_Skill1301.12"
      }
    }
  },
  {
    "Type": "BP_DanmakuLaunchPort_C",
    "Name": "BP_DanmakuLaunchPort1_GEN_VARIABLE",
    "Outer": "BP_Danmaku_BossAida_Skill1301_C",
    "Class": "BlueprintGeneratedClass'EM/Content/BluePrints/Combat/Danmaku/BP_DanmakuLaunchPort.BP_DanmakuLaunchPort_C'",
    "Template": {
      "ObjectName": "BP_DanmakuLaunchPort_C'Default__BP_DanmakuLaunchPort_C'",
      "ObjectPath": "EM/Content/BluePrints/Combat/Danmaku/BP_DanmakuLaunchPort.2"
    },
    "Flags": "RF_Public | RF_Transactional | RF_ArchetypeObject | RF_WasLoaded | RF_LoadCompleted",
    "Properties": {
      "LaunchPortId": 3,
      "CreatureId": 850041,
      "RelativeLocation": {
        "X": 0.0,
        "Y": 0.0,
        "Z": 500.0
      },
      "RelativeRotation": {
        "Pitch": 0.0,
        "Yaw": 45.0,
        "Roll": 0.0
      },
      "bVisible": false,
      "bHiddenInGame": false
    }
  },
  {
    "Type": "BP_DanmakuLaunchPort_C",
    "Name": "BP_DanmakuLaunchPort2_GEN_VARIABLE",
    "Outer": "BP_Danmaku_BossAida_Skill1301_C",
    "Class": "BlueprintGeneratedClass'EM/Content/BluePrints/Combat/Danmaku/BP_DanmakuLaunchPort.BP_DanmakuLaunchPort_C'",
    "Template": {
      "ObjectName": "BP_DanmakuLaunchPort_C'Default__BP_DanmakuLaunchPort_C'",
      "ObjectPath": "EM/Content/BluePrints/Combat/Danmaku/BP_DanmakuLaunchPort.2"
    },
    "Flags": "RF_Public | RF_Transactional | RF_ArchetypeObject | RF_WasLoaded | RF_LoadCompleted",
    "Properties": {
      "LaunchPortId": 3,
      "CreatureId": 850041,
      "RelativeLocation": {
        "X": 0.0,
        "Y": 0.0,
        "Z": 1000.0
      },
      "RelativeRotation": {
        "Pitch": 0.0,
        "Yaw": 45.0,
        "Roll": 0.0
      },
      "bVisible": false,
      "bHiddenInGame": false
    }
  },
  {
    "Type": "BP_DanmakuLaunchPort_C",
    "Name": "BP_DanmakuLaunchPort3_GEN_VARIABLE",
    "Outer": "BP_Danmaku_BossAida_Skill1301_C",
    "Class": "BlueprintGeneratedClass'EM/Content/BluePrints/Combat/Danmaku/BP_DanmakuLaunchPort.BP_DanmakuLaunchPort_C'",
    "Template": {
      "ObjectName": "BP_DanmakuLaunchPort_C'Default__BP_DanmakuLaunchPort_C'",
      "ObjectPath": "EM/Content/BluePrints/Combat/Danmaku/BP_DanmakuLaunchPort.2"
    },
    "Flags": "RF_Public | RF_Transactional | RF_ArchetypeObject | RF_WasLoaded | RF_LoadCompleted",
    "Properties": {
      "LaunchPortId": 3,
      "CreatureId": 850041,
      "RelativeLocation": {
        "X": 0.0,
        "Y": 0.0,
        "Z": 1500.0
      },
      "RelativeRotation": {
        "Pitch": 0.0,
        "Yaw": 45.0,
        "Roll": 0.0
      },
      "bVisible": false,
      "bHiddenInGame": false
    }
  },
  {
    "Type": "BP_DanmakuLaunchPort_C",
    "Name": "BP_DanmakuLaunchPort4_GEN_VARIABLE",
    "Outer": "BP_Danmaku_BossAida_Skill1301_C",
    "Class": "BlueprintGeneratedClass'EM/Content/BluePrints/Combat/Danmaku/BP_DanmakuLaunchPort.BP_DanmakuLaunchPort_C'",
    "Template": {
      "ObjectName": "BP_DanmakuLaunchPort_C'Default__BP_DanmakuLaunchPort_C'",
      "ObjectPath": "EM/Content/BluePrints/Combat/Danmaku/BP_DanmakuLaunchPort.2"
    },
    "Flags": "RF_Public | RF_Transactional | RF_ArchetypeObject | RF_WasLoaded | RF_LoadCompleted",
    "Properties": {
      "LaunchPortId": 3,
      "CreatureId": 850041,
      "RelativeRotation": {
        "Pitch": 0.0,
        "Yaw": -90.0,
        "Roll": 0.0
      },
      "bVisible": false,
      "bHiddenInGame": false
    }
  },
  {
    "Type": "BP_DanmakuLaunchPort_C",
    "Name": "BP_DanmakuLaunchPort5_GEN_VARIABLE",
    "Outer": "BP_Danmaku_BossAida_Skill1301_C",
    "Class": "BlueprintGeneratedClass'EM/Content/BluePrints/Combat/Danmaku/BP_DanmakuLaunchPort.BP_DanmakuLaunchPort_C'",
    "Template": {
      "ObjectName": "BP_DanmakuLaunchPort_C'Default__BP_DanmakuLaunchPort_C'",
      "ObjectPath": "EM/Content/BluePrints/Combat/Danmaku/BP_DanmakuLaunchPort.2"
    },
    "Flags": "RF_Public | RF_Transactional | RF_ArchetypeObject | RF_WasLoaded | RF_LoadCompleted",
    "Properties": {
      "LaunchPortId": 3,
      "CreatureId": 850041,
      "RelativeRotation": {
        "Pitch": 0.0,
        "Yaw": -90.0,
        "Roll": 0.0
      },
      "bVisible": false,
      "bHiddenInGame": false
    }
  },
  {
    "Type": "BP_DanmakuLaunchPort_C",
    "Name": "BP_DanmakuLaunchPort6_GEN_VARIABLE",
    "Outer": "BP_Danmaku_BossAida_Skill1301_C",
    "Class": "BlueprintGeneratedClass'EM/Content/BluePrints/Combat/Danmaku/BP_DanmakuLaunchPort.BP_DanmakuLaunchPort_C'",
    "Template": {
      "ObjectName": "BP_DanmakuLaunchPort_C'Default__BP_DanmakuLaunchPort_C'",
      "ObjectPath": "EM/Content/BluePrints/Combat/Danmaku/BP_DanmakuLaunchPort.2"
    },
    "Flags": "RF_Public | RF_Transactional | RF_ArchetypeObject | RF_WasLoaded | RF_LoadCompleted",
    "Properties": {
      "LaunchPortId": 3,
      "CreatureId": 850041,
      "RelativeRotation": {
        "Pitch": 0.0,
        "Yaw": -90.0,
        "Roll": 0.0
      },
      "bVisible": false,
      "bHiddenInGame": false
    }
  },
  {
    "Type": "BP_DanmakuLaunchPort_C",
    "Name": "BP_DanmakuLaunchPort7_GEN_VARIABLE",
    "Outer": "BP_Danmaku_BossAida_Skill1301_C",
    "Class": "BlueprintGeneratedClass'EM/Content/BluePrints/Combat/Danmaku/BP_DanmakuLaunchPort.BP_DanmakuLaunchPort_C'",
    "Template": {
      "ObjectName": "BP_DanmakuLaunchPort_C'Default__BP_DanmakuLaunchPort_C'",
      "ObjectPath": "EM/Content/BluePrints/Combat/Danmaku/BP_DanmakuLaunchPort.2"
    },
    "Flags": "RF_Public | RF_Transactional | RF_ArchetypeObject | RF_WasLoaded | RF_LoadCompleted",
    "Properties": {
      "LaunchPortId": 3,
      "CreatureId": 850041,
      "RelativeRotation": {
        "Pitch": 0.0,
        "Yaw": -90.0,
        "Roll": 0.0
      },
      "bVisible": false,
      "bHiddenInGame": false
    }
  },
  {
    "Type": "BP_DanmakuLaunchPort_C",
    "Name": "BP_DanmakuLaunchPort_GEN_VARIABLE",
    "Outer": "BP_Danmaku_BossAida_Skill1301_C",
    "Class": "BlueprintGeneratedClass'EM/Content/BluePrints/Combat/Danmaku/BP_DanmakuLaunchPort.BP_DanmakuLaunchPort_C'",
    "Template": {
      "ObjectName": "BP_DanmakuLaunchPort_C'Default__BP_DanmakuLaunchPort_C'",
      "ObjectPath": "EM/Content/BluePrints/Combat/Danmaku/BP_DanmakuLaunchPort.2"
    },
    "Flags": "RF_Public | RF_Transactional | RF_ArchetypeObject | RF_WasLoaded | RF_LoadCompleted",
    "Properties": {
      "LaunchPortId": 3,
      "CreatureId": 850041,
      "RelativeRotation": {
        "Pitch": 0.0,
        "Yaw": 45.0,
        "Roll": 0.0
      },
      "bVisible": false,
      "bHiddenInGame": false
    }
  },
  {
    "Type": "DanmakuInstanceComponent",
    "Name": "DanmakuInstanced",
    "Outer": "Default__BP_Danmaku_BossAida_Skill1301_C",
    "Class": "UScriptClass'DanmakuInstanceComponent'",
    "Template": {
      "ObjectName": "DanmakuInstanceComponent'Default__BP_DanmakuTemplate_C:DanmakuInstanced'",
      "ObjectPath": "EM/Content/BluePrints/Combat/Danmaku/BP_DanmakuTemplate.8"
    },
    "Flags": "RF_Public | RF_Transactional | RF_ArchetypeObject | RF_DefaultSubObject | RF_WasLoaded | RF_LoadCompleted",
    "Properties": {
      "CreatureId": 852001,
      "StaticMesh": {
        "ObjectName": "StaticMesh'mesh_sysplane_yb_001'",
        "ObjectPath": "EM/Content/Asset/Effect/Mesh/Plane/mesh_sysplane_yb_001.2"
      }
    }
  },
  {
    "Type": "InheritableComponentHandler",
    "Name": "InheritableComponentHandler",
    "Outer": "BP_Danmaku_BossAida_Skill1301_C",
    "Class": "UScriptClass'InheritableComponentHandler'",
    "Flags": "RF_WasLoaded | RF_LoadCompleted"
  },
  {
    "Type": "SceneComponent",
    "Name": "DefaultSceneRoot_GEN_VARIABLE",
    "Outer": "BP_Danmaku_BossAida_Skill1301_C",
    "Class": "UScriptClass'SceneComponent'",
    "Flags": "RF_Public | RF_Transactional | RF_ArchetypeObject | RF_WasLoaded | RF_LoadCompleted"
  },
  {
    "Type": "SceneComponent",
    "Name": "PortRoot",
    "Outer": "Default__BP_Danmaku_BossAida_Skill1301_C",
    "Class": "UScriptClass'SceneComponent'",
    "Template": {
      "ObjectName": "SceneComponent'Default__BP_DanmakuTemplate_C:PortRoot'",
      "ObjectPath": "EM/Content/BluePrints/Combat/Danmaku/BP_DanmakuTemplate.10"
    },
    "Flags": "RF_Public | RF_Transactional | RF_ArchetypeObject | RF_DefaultSubObject | RF_WasLoaded | RF_LoadCompleted",
    "Properties": {
      "AttachParent": {
        "ObjectName": "DanmakuInstanceComponent'Default__BP_Danmaku_BossAida_Skill1301_C:DanmakuInstanced'",
        "ObjectPath": "EM/Content/BluePrints/Combat/Danmaku/BP_Danmakus/BP_Danmaku_BossAida_Skill1301.12"
      }
    }
  },
  {
    "Type": "SCS_Node",
    "Name": "SCS_Node_0",
    "Outer": "SimpleConstructionScript_0",
    "Class": "UScriptClass'SCS_Node'",
    "Flags": "RF_Transactional | RF_WasLoaded | RF_LoadCompleted",
    "Properties": {
      "ComponentClass": {
        "ObjectName": "Class'SceneComponent'",
        "ObjectPath": "/Script/Engine"
      },
      "ComponentTemplate": {
        "ObjectName": "SceneComponent'BP_Danmaku_BossAida_Skill1301_C:DefaultSceneRoot_GEN_VARIABLE'",
        "ObjectPath": "EM/Content/BluePrints/Combat/Danmaku/BP_Danmakus/BP_Danmaku_BossAida_Skill1301.14"
      },
      "VariableGuid": "556F11F3-4DEDE679-7E460B91-FDB1897F",
      "InternalVariableName": "DefaultSceneRoot"
    }
  },
  {
    "Type": "SCS_Node",
    "Name": "SCS_Node_1",
    "Outer": "SimpleConstructionScript_0",
    "Class": "UScriptClass'SCS_Node'",
    "Flags": "RF_Transactional | RF_WasLoaded | RF_LoadCompleted",
    "Properties": {
      "ComponentClass": {
        "ObjectName": "BlueprintGeneratedClass'BP_DanmakuLaunchPort_C'",
        "ObjectPath": "EM/Content/BluePrints/Combat/Danmaku/BP_DanmakuLaunchPort.1"
      },
      "ComponentTemplate": {
        "ObjectName": "BP_DanmakuLaunchPort_C'BP_Danmaku_BossAida_Skill1301_C:BP_DanmakuLaunchPort1_GEN_VARIABLE'",
        "ObjectPath": "EM/Content/BluePrints/Combat/Danmaku/BP_Danmakus/BP_Danmaku_BossAida_Skill1301.4"
      },
      "ParentComponentOrVariableName": "DanmakuInstanced",
      "bIsParentComponentNative": true,
      "ChildNodes": [
        {
          "ObjectName": "SCS_Node'BP_Danmaku_BossAida_Skill1301_C:SimpleConstructionScript_0.SCS_Node_6'",
          "ObjectPath": "EM/Content/BluePrints/Combat/Danmaku/BP_Danmakus/BP_Danmaku_BossAida_Skill1301.22"
        }
      ],
      "VariableGuid": "9A524844-4C9EBF7C-18C8B7BA-07DE14A4",
      "InternalVariableName": "BP_DanmakuLaunchPort1"
    }
  },
  {
    "Type": "SCS_Node",
    "Name": "SCS_Node_2",
    "Outer": "SimpleConstructionScript_0",
    "Class": "UScriptClass'SCS_Node'",
    "Flags": "RF_Transactional | RF_WasLoaded | RF_LoadCompleted",
    "Properties": {
      "ComponentClass": {
        "ObjectName": "BlueprintGeneratedClass'BP_DanmakuLaunchPort_C'",
        "ObjectPath": "EM/Content/BluePrints/Combat/Danmaku/BP_DanmakuLaunchPort.1"
      },
      "ComponentTemplate": {
        "ObjectName": "BP_DanmakuLaunchPort_C'BP_Danmaku_BossAida_Skill1301_C:BP_DanmakuLaunchPort2_GEN_VARIABLE'",
        "ObjectPath": "EM/Content/BluePrints/Combat/Danmaku/BP_Danmakus/BP_Danmaku_BossAida_Skill1301.5"
      },
      "ParentComponentOrVariableName": "DanmakuInstanced",
      "bIsParentComponentNative": true,
      "ChildNodes": [
        {
          "ObjectName": "SCS_Node'BP_Danmaku_BossAida_Skill1301_C:SimpleConstructionScript_0.SCS_Node_7'",
          "ObjectPath": "EM/Content/BluePrints/Combat/Danmaku/BP_Danmakus/BP_Danmaku_BossAida_Skill1301.23"
        }
      ],
      "VariableGuid": "0529E307-46681EC5-818E8DB5-84B8A566",
      "InternalVariableName": "BP_DanmakuLaunchPort2"
    }
  },
  {
    "Type": "SCS_Node",
    "Name": "SCS_Node_3",
    "Outer": "SimpleConstructionScript_0",
    "Class": "UScriptClass'SCS_Node'",
    "Flags": "RF_Transactional | RF_WasLoaded | RF_LoadCompleted",
    "Properties": {
      "ComponentClass": {
        "ObjectName": "BlueprintGeneratedClass'BP_DanmakuLaunchPort_C'",
        "ObjectPath": "EM/Content/BluePrints/Combat/Danmaku/BP_DanmakuLaunchPort.1"
      },
      "ComponentTemplate": {
        "ObjectName": "BP_DanmakuLaunchPort_C'BP_Danmaku_BossAida_Skill1301_C:BP_DanmakuLaunchPort_GEN_VARIABLE'",
        "ObjectPath": "EM/Content/BluePrints/Combat/Danmaku/BP_Danmakus/BP_Danmaku_BossAida_Skill1301.11"
      },
      "ParentComponentOrVariableName": "DanmakuInstanced",
      "bIsParentComponentNative": true,
      "ChildNodes": [
        {
          "ObjectName": "SCS_Node'BP_Danmaku_BossAida_Skill1301_C:SimpleConstructionScript_0.SCS_Node_5'",
          "ObjectPath": "EM/Content/BluePrints/Combat/Danmaku/BP_Danmakus/BP_Danmaku_BossAida_Skill1301.21"
        }
      ],
      "VariableGuid": "BF1CED2A-4882B044-830F8CA0-FC62EDAA",
      "InternalVariableName": "BP_DanmakuLaunchPort"
    }
  },
  {
    "Type": "SCS_Node",
    "Name": "SCS_Node_4",
    "Outer": "SimpleConstructionScript_0",
    "Class": "UScriptClass'SCS_Node'",
    "Flags": "RF_Transactional | RF_WasLoaded | RF_LoadCompleted",
    "Properties": {
      "ComponentClass": {
        "ObjectName": "BlueprintGeneratedClass'BP_DanmakuLaunchPort_C'",
        "ObjectPath": "EM/Content/BluePrints/Combat/Danmaku/BP_DanmakuLaunchPort.1"
      },
      "ComponentTemplate": {
        "ObjectName": "BP_DanmakuLaunchPort_C'BP_Danmaku_BossAida_Skill1301_C:BP_DanmakuLaunchPort3_GEN_VARIABLE'",
        "ObjectPath": "EM/Content/BluePrints/Combat/Danmaku/BP_Danmakus/BP_Danmaku_BossAida_Skill1301.6"
      },
      "ParentComponentOrVariableName": "DanmakuInstanced",
      "bIsParentComponentNative": true,
      "ChildNodes": [
        {
          "ObjectName": "SCS_Node'BP_Danmaku_BossAida_Skill1301_C:SimpleConstructionScript_0.SCS_Node_8'",
          "ObjectPath": "EM/Content/BluePrints/Combat/Danmaku/BP_Danmakus/BP_Danmaku_BossAida_Skill1301.24"
        }
      ],
      "VariableGuid": "325DDCDC-4BC1CADF-1D666481-CEC4EBDC",
      "InternalVariableName": "BP_DanmakuLaunchPort3"
    }
  },
  {
    "Type": "SCS_Node",
    "Name": "SCS_Node_5",
    "Outer": "SimpleConstructionScript_0",
    "Class": "UScriptClass'SCS_Node'",
    "Flags": "RF_Transactional | RF_WasLoaded | RF_LoadCompleted",
    "Properties": {
      "ComponentClass": {
        "ObjectName": "BlueprintGeneratedClass'BP_DanmakuLaunchPort_C'",
        "ObjectPath": "EM/Content/BluePrints/Combat/Danmaku/BP_DanmakuLaunchPort.1"
      },
      "ComponentTemplate": {
        "ObjectName": "BP_DanmakuLaunchPort_C'BP_Danmaku_BossAida_Skill1301_C:BP_DanmakuLaunchPort4_GEN_VARIABLE'",
        "ObjectPath": "EM/Content/BluePrints/Combat/Danmaku/BP_Danmakus/BP_Danmaku_BossAida_Skill1301.7"
      },
      "VariableGuid": "01C58061-4AB7CB1C-6BD819BB-0B54CED8",
      "InternalVariableName": "BP_DanmakuLaunchPort4"
    }
  },
  {
    "Type": "SCS_Node",
    "Name": "SCS_Node_6",
    "Outer": "SimpleConstructionScript_0",
    "Class": "UScriptClass'SCS_Node'",
    "Flags": "RF_Transactional | RF_WasLoaded | RF_LoadCompleted",
    "Properties": {
      "ComponentClass": {
        "ObjectName": "BlueprintGeneratedClass'BP_DanmakuLaunchPort_C'",
        "ObjectPath": "EM/Content/BluePrints/Combat/Danmaku/BP_DanmakuLaunchPort.1"
      },
      "ComponentTemplate": {
        "ObjectName": "BP_DanmakuLaunchPort_C'BP_Danmaku_BossAida_Skill1301_C:BP_DanmakuLaunchPort5_GEN_VARIABLE'",
        "ObjectPath": "EM/Content/BluePrints/Combat/Danmaku/BP_Danmakus/BP_Danmaku_BossAida_Skill1301.8"
      },
      "VariableGuid": "3B3FBC8D-49AA71B2-AE696387-CC35B5B7",
      "InternalVariableName": "BP_DanmakuLaunchPort5"
    }
  },
  {
    "Type": "SCS_Node",
    "Name": "SCS_Node_7",
    "Outer": "SimpleConstructionScript_0",
    "Class": "UScriptClass'SCS_Node'",
    "Flags": "RF_Transactional | RF_WasLoaded | RF_LoadCompleted",
    "Properties": {
      "ComponentClass": {
        "ObjectName": "BlueprintGeneratedClass'BP_DanmakuLaunchPort_C'",
        "ObjectPath": "EM/Content/BluePrints/Combat/Danmaku/BP_DanmakuLaunchPort.1"
      },
      "ComponentTemplate": {
        "ObjectName": "BP_DanmakuLaunchPort_C'BP_Danmaku_BossAida_Skill1301_C:BP_DanmakuLaunchPort6_GEN_VARIABLE'",
        "ObjectPath": "EM/Content/BluePrints/Combat/Danmaku/BP_Danmakus/BP_Danmaku_BossAida_Skill1301.9"
      },
      "VariableGuid": "9DFEDBEC-41C40E95-140BAC8E-481FAD3D",
      "InternalVariableName": "BP_DanmakuLaunchPort6"
    }
  },
  {
    "Type": "SCS_Node",
    "Name": "SCS_Node_8",
    "Outer": "SimpleConstructionScript_0",
    "Class": "UScriptClass'SCS_Node'",
    "Flags": "RF_Transactional | RF_WasLoaded | RF_LoadCompleted",
    "Properties": {
      "ComponentClass": {
        "ObjectName": "BlueprintGeneratedClass'BP_DanmakuLaunchPort_C'",
        "ObjectPath": "EM/Content/BluePrints/Combat/Danmaku/BP_DanmakuLaunchPort.1"
      },
      "ComponentTemplate": {
        "ObjectName": "BP_DanmakuLaunchPort_C'BP_Danmaku_BossAida_Skill1301_C:BP_DanmakuLaunchPort7_GEN_VARIABLE'",
        "ObjectPath": "EM/Content/BluePrints/Combat/Danmaku/BP_Danmakus/BP_Danmaku_BossAida_Skill1301.10"
      },
      "VariableGuid": "34FF3E75-400A2BC8-0C2FA784-96BF9DA1",
      "InternalVariableName": "BP_DanmakuLaunchPort7"
    }
  },
  {
    "Type": "SimpleConstructionScript",
    "Name": "SimpleConstructionScript_0",
    "Outer": "BP_Danmaku_BossAida_Skill1301_C",
    "Class": "UScriptClass'SimpleConstructionScript'",
    "Flags": "RF_Transactional | RF_WasLoaded | RF_LoadCompleted",
    "Properties": {
      "RootNodes": [
        {
          "ObjectName": "SCS_Node'BP_Danmaku_BossAida_Skill1301_C:SimpleConstructionScript_0.SCS_Node_3'",
          "ObjectPath": "EM/Content/BluePrints/Combat/Danmaku/BP_Danmakus/BP_Danmaku_BossAida_Skill1301.19"
        },
        {
          "ObjectName": "SCS_Node'BP_Danmaku_BossAida_Skill1301_C:SimpleConstructionScript_0.SCS_Node_1'",
          "ObjectPath": "EM/Content/BluePrints/Combat/Danmaku/BP_Danmakus/BP_Danmaku_BossAida_Skill1301.17"
        },
        {
          "ObjectName": "SCS_Node'BP_Danmaku_BossAida_Skill1301_C:SimpleConstructionScript_0.SCS_Node_2'",
          "ObjectPath": "EM/Content/BluePrints/Combat/Danmaku/BP_Danmakus/BP_Danmaku_BossAida_Skill1301.18"
        },
        {
          "ObjectName": "SCS_Node'BP_Danmaku_BossAida_Skill1301_C:SimpleConstructionScript_0.SCS_Node_4'",
          "ObjectPath": "EM/Content/BluePrints/Combat/Danmaku/BP_Danmakus/BP_Danmaku_BossAida_Skill1301.20"
        }
      ],
      "AllNodes": [
        {
          "ObjectName": "SCS_Node'BP_Danmaku_BossAida_Skill1301_C:SimpleConstructionScript_0.SCS_Node_3'",
          "ObjectPath": "EM/Content/BluePrints/Combat/Danmaku/BP_Danmakus/BP_Danmaku_BossAida_Skill1301.19"
        },
        {
          "ObjectName": "SCS_Node'BP_Danmaku_BossAida_Skill1301_C:SimpleConstructionScript_0.SCS_Node_1'",
          "ObjectPath": "EM/Content/BluePrints/Combat/Danmaku/BP_Danmakus/BP_Danmaku_BossAida_Skill1301.17"
        },
        {
          "ObjectName": "SCS_Node'BP_Danmaku_BossAida_Skill1301_C:SimpleConstructionScript_0.SCS_Node_2'",
          "ObjectPath": "EM/Content/BluePrints/Combat/Danmaku/BP_Danmakus/BP_Danmaku_BossAida_Skill1301.18"
        },
        {
          "ObjectName": "SCS_Node'BP_Danmaku_BossAida_Skill1301_C:SimpleConstructionScript_0.SCS_Node_4'",
          "ObjectPath": "EM/Content/BluePrints/Combat/Danmaku/BP_Danmakus/BP_Danmaku_BossAida_Skill1301.20"
        },
        {
          "ObjectName": "SCS_Node'BP_Danmaku_BossAida_Skill1301_C:SimpleConstructionScript_0.SCS_Node_5'",
          "ObjectPath": "EM/Content/BluePrints/Combat/Danmaku/BP_Danmakus/BP_Danmaku_BossAida_Skill1301.21"
        },
        {
          "ObjectName": "SCS_Node'BP_Danmaku_BossAida_Skill1301_C:SimpleConstructionScript_0.SCS_Node_6'",
          "ObjectPath": "EM/Content/BluePrints/Combat/Danmaku/BP_Danmakus/BP_Danmaku_BossAida_Skill1301.22"
        },
        {
          "ObjectName": "SCS_Node'BP_Danmaku_BossAida_Skill1301_C:SimpleConstructionScript_0.SCS_Node_7'",
          "ObjectPath": "EM/Content/BluePrints/Combat/Danmaku/BP_Danmakus/BP_Danmaku_BossAida_Skill1301.23"
        },
        {
          "ObjectName": "SCS_Node'BP_Danmaku_BossAida_Skill1301_C:SimpleConstructionScript_0.SCS_Node_8'",
          "ObjectPath": "EM/Content/BluePrints/Combat/Danmaku/BP_Danmakus/BP_Danmaku_BossAida_Skill1301.24"
        }
      ],
      "DefaultSceneRootNode": {
        "ObjectName": "SCS_Node'BP_Danmaku_BossAida_Skill1301_C:SimpleConstructionScript_0.SCS_Node_0'",
        "ObjectPath": "EM/Content/BluePrints/Combat/Danmaku/BP_Danmakus/BP_Danmaku_BossAida_Skill1301.16"
      }
    }
  }
]