[
  {
    "Type": "Function",
    "Name": "SummonSwitch__DelegateSignature",
    "Outer": "BP_Feina_Summon_C",
    "Class": "UScriptClass'Function'",
    "Flags": "RF_Public | RF_WasLoaded | RF_LoadCompleted",
    "FunctionFlags": "FUNC_Public | FUNC_Delegate | FUNC_BlueprintCallable | FUNC_BlueprintEvent"
  },
  {
    "Type": "Function",
    "Name": "ExecuteUbergraph_BP_Feina_Summon",
    "Outer": "BP_Feina_Summon_C",
    "Class": "UScriptClass'Function'",
    "Flags": "RF_Public | RF_WasLoaded | RF_LoadCompleted",
    "ChildProperties": [
      {
        "Type": "IntProperty",
        "Name": "EntryPoint",
        "Flags": "RF_Public",
        "ElementSize": 4,
        "PropertyFlags": "BlueprintVisible | BlueprintReadOnly | Parm"
      },
      {
        "Type": "StructProperty",
        "Name": "CallFunc_GetSocketTransform_ReturnValue",
        "Flags": "RF_Public",
        "ElementSize": 48,
        "Struct": {
          "ObjectName": "ScriptStruct'Transform'",
          "ObjectPath": "/Script/CoreUObject"
        }
      },
      {
        "Type": "StructProperty",
        "Name": "CallFunc_BreakTransform_Location",
        "Flags": "RF_Public",
        "ElementSize": 12,
        "Struct": {
          "ObjectName": "ScriptStruct'Vector'",
          "ObjectPath": "/Script/CoreUObject"
        }
      },
      {
        "Type": "StructProperty",
        "Name": "CallFunc_BreakTransform_Rotation",
        "Flags": "RF_Public",
        "ElementSize": 12,
        "Struct": {
          "ObjectName": "ScriptStruct'Rotator'",
          "ObjectPath": "/Script/CoreUObject"
        }
      },
      {
        "Type": "StructProperty",
        "Name": "CallFunc_BreakTransform_Scale",
        "Flags": "RF_Public",
        "ElementSize": 12,
        "Struct": {
          "ObjectName": "ScriptStruct'Vector'",
          "ObjectPath": "/Script/CoreUObject"
        }
      },
      {
        "Type": "BoolProperty",
        "Name": "___bool_IsClosed_Variable",
        "Flags": "RF_Public",
        "ElementSize": 1,
        "FieldSize": 1,
        "ByteOffset": 0,
        "ByteMask": 1,
        "FieldMask": 255,
        "BoolSize": 1,
        "bIsNativeBool": true
      },
      {
        "Type": "BoolProperty",
        "Name": "___bool_IsClosed_Variable_1",
        "Flags": "RF_Public",
        "ElementSize": 1,
        "FieldSize": 1,
        "ByteOffset": 0,
        "ByteMask": 1,
        "FieldMask": 255,
        "BoolSize": 1,
        "bIsNativeBool": true
      },
      {
        "Type": "BoolProperty",
        "Name": "___bool_Has_Been_Initd_Variable",
        "Flags": "RF_Public",
        "ElementSize": 1,
        "FieldSize": 1,
        "ByteOffset": 0,
        "ByteMask": 1,
        "FieldMask": 255,
        "BoolSize": 1,
        "bIsNativeBool": true
      },
      {
        "Type": "InterfaceProperty",
        "Name": "CallFunc_RemoveBuffsByBuffType_Source_CastInput",
        "Flags": "RF_Public",
        "ElementSize": 16,
        "PropertyFlags": "ConstParm | UObjectWrapper",
        "InterfaceClass": {
          "ObjectName": "Class'EffectSourceInterface'",
          "ObjectPath": "/Script/EM"
        }
      },
      {
        "Type": "InterfaceProperty",
        "Name": "CallFunc_RemoveBuffsByBuffType_Target_CastInput",
        "Flags": "RF_Public",
        "ElementSize": 16,
        "PropertyFlags": "ConstParm | UObjectWrapper",
        "InterfaceClass": {
          "ObjectName": "Class'EffectSourceInterface'",
          "ObjectPath": "/Script/EM"
        }
      },
      {
        "Type": "IntProperty",
        "Name": "CallFunc_Multiply_IntInt_ReturnValue",
        "Flags": "RF_Public",
        "ElementSize": 4
      },
      {
        "Type": "InterfaceProperty",
        "Name": "CallFunc_GetCreator_Target_CastInput",
        "Flags": "RF_Public",
        "ElementSize": 16,
        "PropertyFlags": "ConstParm | UObjectWrapper",
        "InterfaceClass": {
          "ObjectName": "Class'EffectSourceInterface'",
          "ObjectPath": "/Script/EM"
        }
      },
      {
        "Type": "InterfaceProperty",
        "Name": "CallFunc_GetCreator_ReturnValue",
        "Flags": "RF_Public",
        "ElementSize": 16,
        "PropertyFlags": "UObjectWrapper",
        "InterfaceClass": {
          "ObjectName": "Class'EffectSourceInterface'",
          "ObjectPath": "/Script/EM"
        }
      },
      {
        "Type": "IntProperty",
        "Name": "CallFunc_Add_IntInt_ReturnValue",
        "Flags": "RF_Public",
        "ElementSize": 4
      },
      {
        "Type": "BoolProperty",
        "Name": "CallFunc_IsEffectSourceValid_ReturnValue",
        "Flags": "RF_Public",
        "ElementSize": 1,
        "FieldSize": 1,
        "ByteOffset": 0,
        "ByteMask": 1,
        "FieldMask": 255,
        "BoolSize": 1,
        "bIsNativeBool": true
      },
      {
        "Type": "FloatProperty",
        "Name": "CallFunc_GetAttr_ByEnum_ReturnValue",
        "Flags": "RF_Public",
        "ElementSize": 4
      },
      {
        "Type": "InterfaceProperty",
        "Name": "CallFunc_AddBuffToTarget_Target_CastInput",
        "Flags": "RF_Public",
        "ElementSize": 16,
        "PropertyFlags": "ConstParm | UObjectWrapper",
        "InterfaceClass": {
          "ObjectName": "Class'EffectSourceInterface'",
          "ObjectPath": "/Script/EM"
        }
      },
      {
        "Type": "InterfaceProperty",
        "Name": "CallFunc_AddBuffToTarget_SkillLevelSource_CastInput",
        "Flags": "RF_Public",
        "ElementSize": 16,
        "PropertyFlags": "ConstParm | UObjectWrapper",
        "InterfaceClass": {
          "ObjectName": "Class'SkillLevelInterface'",
          "ObjectPath": "/Script/EM"
        }
      },
      {
        "Type": "ArrayProperty",
        "Name": "CallFunc_AddBuffToTarget_ReturnValue",
        "Flags": "RF_Public",
        "ElementSize": 16,
        "PropertyFlags": "ReferenceParm",
        "Inner": {
          "Type": "ObjectProperty",
          "Name": "CallFunc_AddBuffToTarget_ReturnValue",
          "Flags": "RF_Public",
          "ElementSize": 8,
          "PropertyClass": {
            "ObjectName": "Class'Buff'",
            "ObjectPath": "/Script/EM"
          }
        }
      },
      {
        "Type": "InterfaceProperty",
        "Name": "CallFunc_GetCreator_Target_CastInput_1",
        "Flags": "RF_Public",
        "ElementSize": 16,
        "PropertyFlags": "ConstParm | UObjectWrapper",
        "InterfaceClass": {
          "ObjectName": "Class'EffectSourceInterface'",
          "ObjectPath": "/Script/EM"
        }
      },
      {
        "Type": "InterfaceProperty",
        "Name": "CallFunc_GetCreator_ReturnValue_1",
        "Flags": "RF_Public",
        "ElementSize": 16,
        "PropertyFlags": "UObjectWrapper",
        "InterfaceClass": {
          "ObjectName": "Class'EffectSourceInterface'",
          "ObjectPath": "/Script/EM"
        }
      },
      {
        "Type": "ObjectProperty",
        "Name": "CallFunc_CastToCharacterBase_ReturnValue",
        "Flags": "RF_Public",
        "ElementSize": 8,
        "PropertyClass": {
          "ObjectName": "Class'CharacterBase'",
          "ObjectPath": "/Script/EM"
        }
      },
      {
        "Type": "ObjectProperty",
        "Name": "CallFunc_GetBlackboard_ReturnValue",
        "Flags": "RF_Public",
        "ElementSize": 8,
        "PropertyFlags": "InstancedReference",
        "PropertyClass": {
          "ObjectName": "Class'BlackboardComponent'",
          "ObjectPath": "/Script/AIModule"
        }
      },
      {
        "Type": "InterfaceProperty",
        "Name": "CallFunc_GetFloat_Source_CastInput",
        "Flags": "RF_Public",
        "ElementSize": 16,
        "PropertyFlags": "ConstParm | UObjectWrapper",
        "InterfaceClass": {
          "ObjectName": "Class'DataSetInterface'",
          "ObjectPath": "/Script/EM"
        }
      },
      {
        "Type": "FloatProperty",
        "Name": "CallFunc_GetFloat_ReturnValue",
        "Flags": "RF_Public",
        "ElementSize": 4
      },
      {
        "Type": "BoolProperty",
        "Name": "CallFunc_IsValid_ReturnValue",
        "Flags": "RF_Public",
        "ElementSize": 1,
        "FieldSize": 1,
        "ByteOffset": 0,
        "ByteMask": 1,
        "FieldMask": 255,
        "BoolSize": 1,
        "bIsNativeBool": true
      },
      {
        "Type": "StructProperty",
        "Name": "CallFunc_MakeRotator_ReturnValue",
        "Flags": "RF_Public",
        "ElementSize": 12,
        "Struct": {
          "ObjectName": "ScriptStruct'Rotator'",
          "ObjectPath": "/Script/CoreUObject"
        }
      },
      {
        "Type": "BoolProperty",
        "Name": "CallFunc_K2_SetActorRotation_ReturnValue",
        "Flags": "RF_Public",
        "ElementSize": 1,
        "FieldSize": 1,
        "ByteOffset": 0,
        "ByteMask": 1,
        "FieldMask": 255,
        "BoolSize": 1,
        "bIsNativeBool": true
      },
      {
        "Type": "ObjectProperty",
        "Name": "CallFunc_GetSkill_ReturnValue",
        "Flags": "RF_Public",
        "ElementSize": 8,
        "PropertyClass": {
          "ObjectName": "Class'SkillObject'",
          "ObjectPath": "/Script/EM"
        }
      },
      {
        "Type": "InterfaceProperty",
        "Name": "CallFunc_GetFloat_Source_CastInput_1",
        "Flags": "RF_Public",
        "ElementSize": 16,
        "PropertyFlags": "ConstParm | UObjectWrapper",
        "InterfaceClass": {
          "ObjectName": "Class'DataSetInterface'",
          "ObjectPath": "/Script/EM"
        }
      },
      {
        "Type": "FloatProperty",
        "Name": "CallFunc_GetFloat_ReturnValue_1",
        "Flags": "RF_Public",
        "ElementSize": 4
      },
      {
        "Type": "InterfaceProperty",
        "Name": "CallFunc_GetInt_Source_CastInput",
        "Flags": "RF_Public",
        "ElementSize": 16,
        "PropertyFlags": "ConstParm | UObjectWrapper",
        "InterfaceClass": {
          "ObjectName": "Class'DataSetInterface'",
          "ObjectPath": "/Script/EM"
        }
      },
      {
        "Type": "IntProperty",
        "Name": "CallFunc_GetInt_ReturnValue",
        "Flags": "RF_Public",
        "ElementSize": 4
      },
      {
        "Type": "ObjectProperty",
        "Name": "CallFunc_GetSkill_ReturnValue_1",
        "Flags": "RF_Public",
        "ElementSize": 8,
        "PropertyClass": {
          "ObjectName": "Class'SkillObject'",
          "ObjectPath": "/Script/EM"
        }
      },
      {
        "Type": "BoolProperty",
        "Name": "___bool_Has_Been_Initd_Variable_1",
        "Flags": "RF_Public",
        "ElementSize": 1,
        "FieldSize": 1,
        "ByteOffset": 0,
        "ByteMask": 1,
        "FieldMask": 255,
        "BoolSize": 1,
        "bIsNativeBool": true
      },
      {
        "Type": "InterfaceProperty",
        "Name": "CallFunc_AddBuffToTarget_SkillLevelSource_CastInput_1",
        "Flags": "RF_Public",
        "ElementSize": 16,
        "PropertyFlags": "ConstParm | UObjectWrapper",
        "InterfaceClass": {
          "ObjectName": "Class'SkillLevelInterface'",
          "ObjectPath": "/Script/EM"
        }
      },
      {
        "Type": "ArrayProperty",
        "Name": "CallFunc_AddBuffToTarget_ReturnValue_1",
        "Flags": "RF_Public",
        "ElementSize": 16,
        "PropertyFlags": "ReferenceParm",
        "Inner": {
          "Type": "ObjectProperty",
          "Name": "CallFunc_AddBuffToTarget_ReturnValue_1",
          "Flags": "RF_Public",
          "ElementSize": 8,
          "PropertyClass": {
            "ObjectName": "Class'Buff'",
            "ObjectPath": "/Script/EM"
          }
        }
      },
      {
        "Type": "BoolProperty",
        "Name": "CallFunc_CheckSkillGrade_IsSuccess",
        "Flags": "RF_Public",
        "ElementSize": 1,
        "FieldSize": 1,
        "ByteOffset": 0,
        "ByteMask": 1,
        "FieldMask": 255,
        "BoolSize": 1,
        "bIsNativeBool": true
      },
      {
        "Type": "InterfaceProperty",
        "Name": "CallFunc_AddBuffToTarget_SkillLevelSource_CastInput_2",
        "Flags": "RF_Public",
        "ElementSize": 16,
        "PropertyFlags": "ConstParm | UObjectWrapper",
        "InterfaceClass": {
          "ObjectName": "Class'SkillLevelInterface'",
          "ObjectPath": "/Script/EM"
        }
      },
      {
        "Type": "ArrayProperty",
        "Name": "CallFunc_AddBuffToTarget_ReturnValue_2",
        "Flags": "RF_Public",
        "ElementSize": 16,
        "PropertyFlags": "ReferenceParm",
        "Inner": {
          "Type": "ObjectProperty",
          "Name": "CallFunc_AddBuffToTarget_ReturnValue_2",
          "Flags": "RF_Public",
          "ElementSize": 8,
          "PropertyClass": {
            "ObjectName": "Class'Buff'",
            "ObjectPath": "/Script/EM"
          }
        }
      },
      {
        "Type": "BoolProperty",
        "Name": "K2Node_CustomEvent_Reset",
        "Flags": "RF_Public",
        "ElementSize": 1,
        "FieldSize": 1,
        "ByteOffset": 0,
        "ByteMask": 1,
        "FieldMask": 255,
        "BoolSize": 1,
        "bIsNativeBool": true
      },
      {
        "Type": "IntProperty",
        "Name": "CallFunc_Add_IntInt_ReturnValue_1",
        "Flags": "RF_Public",
        "ElementSize": 4
      },
      {
        "Type": "StructProperty",
        "Name": "CallFunc_GetSocketTransform_ReturnValue_1",
        "Flags": "RF_Public",
        "ElementSize": 48,
        "Struct": {
          "ObjectName": "ScriptStruct'Transform'",
          "ObjectPath": "/Script/CoreUObject"
        }
      },
      {
        "Type": "StructProperty",
        "Name": "CallFunc_BreakTransform_Location_1",
        "Flags": "RF_Public",
        "ElementSize": 12,
        "Struct": {
          "ObjectName": "ScriptStruct'Vector'",
          "ObjectPath": "/Script/CoreUObject"
        }
      },
      {
        "Type": "StructProperty",
        "Name": "CallFunc_BreakTransform_Rotation_1",
        "Flags": "RF_Public",
        "ElementSize": 12,
        "Struct": {
          "ObjectName": "ScriptStruct'Rotator'",
          "ObjectPath": "/Script/CoreUObject"
        }
      },
      {
        "Type": "StructProperty",
        "Name": "CallFunc_BreakTransform_Scale_1",
        "Flags": "RF_Public",
        "ElementSize": 12,
        "Struct": {
          "ObjectName": "ScriptStruct'Vector'",
          "ObjectPath": "/Script/CoreUObject"
        }
      },
      {
        "Type": "BoolProperty",
        "Name": "K2Node_SwitchInteger_CmpSuccess",
        "Flags": "RF_Public",
        "ElementSize": 1,
        "FieldSize": 1,
        "ByteOffset": 0,
        "ByteMask": 1,
        "FieldMask": 255,
        "BoolSize": 1,
        "bIsNativeBool": true
      },
      {
        "Type": "InterfaceProperty",
        "Name": "CallFunc_GetCreator_Target_CastInput_2",
        "Flags": "RF_Public",
        "ElementSize": 16,
        "PropertyFlags": "ConstParm | UObjectWrapper",
        "InterfaceClass": {
          "ObjectName": "Class'EffectSourceInterface'",
          "ObjectPath": "/Script/EM"
        }
      },
      {
        "Type": "InterfaceProperty",
        "Name": "CallFunc_GetCreator_ReturnValue_2",
        "Flags": "RF_Public",
        "ElementSize": 16,
        "PropertyFlags": "UObjectWrapper",
        "InterfaceClass": {
          "ObjectName": "Class'EffectSourceInterface'",
          "ObjectPath": "/Script/EM"
        }
      },
      {
        "Type": "ObjectProperty",
        "Name": "CallFunc_CastToCharacterBase_ReturnValue_1",
        "Flags": "RF_Public",
        "ElementSize": 8,
        "PropertyClass": {
          "ObjectName": "Class'CharacterBase'",
          "ObjectPath": "/Script/EM"
        }
      },
      {
        "Type": "ObjectProperty",
        "Name": "CallFunc_GetSkill_ReturnValue_2",
        "Flags": "RF_Public",
        "ElementSize": 8,
        "PropertyClass": {
          "ObjectName": "Class'SkillObject'",
          "ObjectPath": "/Script/EM"
        }
      },
      {
        "Type": "InterfaceProperty",
        "Name": "CallFunc_GetCreator_Target_CastInput_3",
        "Flags": "RF_Public",
        "ElementSize": 16,
        "PropertyFlags": "ConstParm | UObjectWrapper",
        "InterfaceClass": {
          "ObjectName": "Class'EffectSourceInterface'",
          "ObjectPath": "/Script/EM"
        }
      },
      {
        "Type": "InterfaceProperty",
        "Name": "CallFunc_GetCreator_ReturnValue_3",
        "Flags": "RF_Public",
        "ElementSize": 16,
        "PropertyFlags": "UObjectWrapper",
        "InterfaceClass": {
          "ObjectName": "Class'EffectSourceInterface'",
          "ObjectPath": "/Script/EM"
        }
      },
      {
        "Type": "ArrayProperty",
        "Name": "CallFunc_FindBuffsByBuffType_ReturnValue",
        "Flags": "RF_Public",
        "ElementSize": 16,
        "PropertyFlags": "ReferenceParm",
        "Inner": {
          "Type": "ObjectProperty",
          "Name": "CallFunc_FindBuffsByBuffType_ReturnValue",
          "Flags": "RF_Public",
          "ElementSize": 8,
          "PropertyClass": {
            "ObjectName": "Class'Buff'",
            "ObjectPath": "/Script/EM"
          }
        }
      },
      {
        "Type": "ObjectProperty",
        "Name": "CallFunc_CastToCharacterBase_ReturnValue_2",
        "Flags": "RF_Public",
        "ElementSize": 8,
        "PropertyClass": {
          "ObjectName": "Class'CharacterBase'",
          "ObjectPath": "/Script/EM"
        }
      },
      {
        "Type": "IntProperty",
        "Name": "CallFunc_Array_Length_ReturnValue",
        "Flags": "RF_Public",
        "ElementSize": 4
      },
      {
        "Type": "BoolProperty",
        "Name": "CallFunc_GreaterEqual_IntInt_ReturnValue",
        "Flags": "RF_Public",
        "ElementSize": 1,
        "FieldSize": 1,
        "ByteOffset": 0,
        "ByteMask": 1,
        "FieldMask": 255,
        "BoolSize": 1,
        "bIsNativeBool": true
      },
      {
        "Type": "IntProperty",
        "Name": "CallFunc_Add_IntInt_ReturnValue_2",
        "Flags": "RF_Public",
        "ElementSize": 4
      },
      {
        "Type": "BoolProperty",
        "Name": "CallFunc_IsValid_ReturnValue_1",
        "Flags": "RF_Public",
        "ElementSize": 1,
        "FieldSize": 1,
        "ByteOffset": 0,
        "ByteMask": 1,
        "FieldMask": 255,
        "BoolSize": 1,
        "bIsNativeBool": true
      },
      {
        "Type": "BoolProperty",
        "Name": "CallFunc_IsValid_ReturnValue_2",
        "Flags": "RF_Public",
        "ElementSize": 1,
        "FieldSize": 1,
        "ByteOffset": 0,
        "ByteMask": 1,
        "FieldMask": 255,
        "BoolSize": 1,
        "bIsNativeBool": true
      },
      {
        "Type": "BoolProperty",
        "Name": "CallFunc_IsStandAloneOrClient_ReturnValue",
        "Flags": "RF_Public",
        "ElementSize": 1,
        "PropertyFlags": "ConstParm",
        "FieldSize": 1,
        "ByteOffset": 0,
        "ByteMask": 1,
        "FieldMask": 255,
        "BoolSize": 1,
        "bIsNativeBool": true
      },
      {
        "Type": "DelegateProperty",
        "Name": "K2Node_CreateDelegate_OutputDelegate",
        "Flags": "RF_Public",
        "ElementSize": 20,
        "SignatureFunction": {
          "ObjectName": "DelegateFunction'TimerDynamicDelegate__DelegateSignature'",
          "ObjectPath": "/Script/Engine"
        }
      },
      {
        "Type": "StructProperty",
        "Name": "CallFunc_Array_Get_Item",
        "Flags": "RF_Public",
        "ElementSize": 16,
        "Struct": {
          "ObjectName": "ScriptStruct'LinearColor'",
          "ObjectPath": "/Script/CoreUObject"
        }
      },
      {
        "Type": "ObjectProperty",
        "Name": "CallFunc_Array_Get_Item_1",
        "Flags": "RF_Public",
        "ElementSize": 8,
        "PropertyClass": {
          "ObjectName": "Class'NiagaraSystem'",
          "ObjectPath": "/Script/Niagara"
        }
      },
      {
        "Type": "BoolProperty",
        "Name": "CallFunc_IsValid_ReturnValue_3",
        "Flags": "RF_Public",
        "ElementSize": 1,
        "FieldSize": 1,
        "ByteOffset": 0,
        "ByteMask": 1,
        "FieldMask": 255,
        "BoolSize": 1,
        "bIsNativeBool": true
      },
      {
        "Type": "BoolProperty",
        "Name": "CallFunc_IsValid_ReturnValue_4",
        "Flags": "RF_Public",
        "ElementSize": 1,
        "FieldSize": 1,
        "ByteOffset": 0,
        "ByteMask": 1,
        "FieldMask": 255,
        "BoolSize": 1,
        "bIsNativeBool": true
      },
      {
        "Type": "BoolProperty",
        "Name": "CallFunc_CheckSkillGrade_IsSuccess_1",
        "Flags": "RF_Public",
        "ElementSize": 1,
        "FieldSize": 1,
        "ByteOffset": 0,
        "ByteMask": 1,
        "FieldMask": 255,
        "BoolSize": 1,
        "bIsNativeBool": true
      },
      {
        "Type": "InterfaceProperty",
        "Name": "CallFunc_GetCreator_Target_CastInput_4",
        "Flags": "RF_Public",
        "ElementSize": 16,
        "PropertyFlags": "ConstParm | UObjectWrapper",
        "InterfaceClass": {
          "ObjectName": "Class'EffectSourceInterface'",
          "ObjectPath": "/Script/EM"
        }
      },
      {
        "Type": "InterfaceProperty",
        "Name": "CallFunc_GetCreator_ReturnValue_4",
        "Flags": "RF_Public",
        "ElementSize": 16,
        "PropertyFlags": "UObjectWrapper",
        "InterfaceClass": {
          "ObjectName": "Class'EffectSourceInterface'",
          "ObjectPath": "/Script/EM"
        }
      },
      {
        "Type": "BoolProperty",
        "Name": "CallFunc_RemoveBuffFromTarget_ReturnValue",
        "Flags": "RF_Public",
        "ElementSize": 1,
        "FieldSize": 1,
        "ByteOffset": 0,
        "ByteMask": 1,
        "FieldMask": 255,
        "BoolSize": 1,
        "bIsNativeBool": true
      },
      {
        "Type": "ObjectProperty",
        "Name": "CallFunc_CastToCharacterBase_ReturnValue_3",
        "Flags": "RF_Public",
        "ElementSize": 8,
        "PropertyClass": {
          "ObjectName": "Class'CharacterBase'",
          "ObjectPath": "/Script/EM"
        }
      },
      {
        "Type": "BoolProperty",
        "Name": "CallFunc_IsValid_ReturnValue_5",
        "Flags": "RF_Public",
        "ElementSize": 1,
        "FieldSize": 1,
        "ByteOffset": 0,
        "ByteMask": 1,
        "FieldMask": 255,
        "BoolSize": 1,
        "bIsNativeBool": true
      },
      {
        "Type": "BoolProperty",
        "Name": "K2Node_SwitchInteger_CmpSuccess_1",
        "Flags": "RF_Public",
        "ElementSize": 1,
        "FieldSize": 1,
        "ByteOffset": 0,
        "ByteMask": 1,
        "FieldMask": 255,
        "BoolSize": 1,
        "bIsNativeBool": true
      },
      {
        "Type": "BoolProperty",
        "Name": "CallFunc_IsValid_ReturnValue_6",
        "Flags": "RF_Public",
        "ElementSize": 1,
        "FieldSize": 1,
        "ByteOffset": 0,
        "ByteMask": 1,
        "FieldMask": 255,
        "BoolSize": 1,
        "bIsNativeBool": true
      },
      {
        "Type": "BoolProperty",
        "Name": "CallFunc_IsValid_ReturnValue_7",
        "Flags": "RF_Public",
        "ElementSize": 1,
        "FieldSize": 1,
        "ByteOffset": 0,
        "ByteMask": 1,
        "FieldMask": 255,
        "BoolSize": 1,
        "bIsNativeBool": true
      },
      {
        "Type": "InterfaceProperty",
        "Name": "CallFunc_GetCreator_Target_CastInput_5",
        "Flags": "RF_Public",
        "ElementSize": 16,
        "PropertyFlags": "ConstParm | UObjectWrapper",
        "InterfaceClass": {
          "ObjectName": "Class'EffectSourceInterface'",
          "ObjectPath": "/Script/EM"
        }
      },
      {
        "Type": "InterfaceProperty",
        "Name": "CallFunc_GetCreator_ReturnValue_5",
        "Flags": "RF_Public",
        "ElementSize": 16,
        "PropertyFlags": "UObjectWrapper",
        "InterfaceClass": {
          "ObjectName": "Class'EffectSourceInterface'",
          "ObjectPath": "/Script/EM"
        }
      },
      {
        "Type": "StructProperty",
        "Name": "CallFunc_GetSocketTransform_ReturnValue_2",
        "Flags": "RF_Public",
        "ElementSize": 48,
        "Struct": {
          "ObjectName": "ScriptStruct'Transform'",
          "ObjectPath": "/Script/CoreUObject"
        }
      },
      {
        "Type": "ObjectProperty",
        "Name": "CallFunc_CastToCharacterBase_ReturnValue_4",
        "Flags": "RF_Public",
        "ElementSize": 8,
        "PropertyClass": {
          "ObjectName": "Class'CharacterBase'",
          "ObjectPath": "/Script/EM"
        }
      },
      {
        "Type": "ObjectProperty",
        "Name": "CallFunc_CreateEffectCreature_ReturnValue",
        "Flags": "RF_Public",
        "ElementSize": 8,
        "PropertyClass": {
          "ObjectName": "Class'EffectCreature'",
          "ObjectPath": "/Script/EM"
        }
      },
      {
        "Type": "InterfaceProperty",
        "Name": "CallFunc_GetCreator_Target_CastInput_6",
        "Flags": "RF_Public",
        "ElementSize": 16,
        "PropertyFlags": "ConstParm | UObjectWrapper",
        "InterfaceClass": {
          "ObjectName": "Class'EffectSourceInterface'",
          "ObjectPath": "/Script/EM"
        }
      },
      {
        "Type": "InterfaceProperty",
        "Name": "CallFunc_GetCreator_ReturnValue_6",
        "Flags": "RF_Public",
        "ElementSize": 16,
        "PropertyFlags": "UObjectWrapper",
        "InterfaceClass": {
          "ObjectName": "Class'EffectSourceInterface'",
          "ObjectPath": "/Script/EM"
        }
      },
      {
        "Type": "ObjectProperty",
        "Name": "K2Node_DynamicCast_AsBP_Effect_Creature_Feina_Summon",
        "Flags": "RF_Public",
        "ElementSize": 8,
        "PropertyClass": {
          "ObjectName": "BlueprintGeneratedClass'BP_EffectCreature_Feina_Summon_C'",
          "ObjectPath": "EM/Content/BluePrints/Combat/EffectCreature/Skill/BP_EffectCreature_Feina_Summon.7"
        }
      },
      {
        "Type": "BoolProperty",
        "Name": "K2Node_DynamicCast_bSuccess",
        "Flags": "RF_Public",
        "ElementSize": 1,
        "FieldSize": 1,
        "ByteOffset": 0,
        "ByteMask": 1,
        "FieldMask": 255,
        "BoolSize": 1,
        "bIsNativeBool": true
      },
      {
        "Type": "ObjectProperty",
        "Name": "CallFunc_CastToCharacterBase_ReturnValue_5",
        "Flags": "RF_Public",
        "ElementSize": 8,
        "PropertyClass": {
          "ObjectName": "Class'CharacterBase'",
          "ObjectPath": "/Script/EM"
        }
      },
      {
        "Type": "ObjectProperty",
        "Name": "CallFunc_GetController_ReturnValue",
        "Flags": "RF_Public",
        "ElementSize": 8,
        "PropertyClass": {
          "ObjectName": "Class'Controller'",
          "ObjectPath": "/Script/Engine"
        }
      },
      {
        "Type": "FloatProperty",
        "Name": "CallFunc_SkillRangeModifier_ModifyResult",
        "Flags": "RF_Public",
        "ElementSize": 4
      },
      {
        "Type": "ObjectProperty",
        "Name": "K2Node_DynamicCast_As_____",
        "Flags": "RF_Public",
        "ElementSize": 8,
        "PropertyClass": {
          "ObjectName": "Class'PlayerController'",
          "ObjectPath": "/Script/Engine"
        }
      },
      {
        "Type": "BoolProperty",
        "Name": "K2Node_DynamicCast_bSuccess_1",
        "Flags": "RF_Public",
        "ElementSize": 1,
        "FieldSize": 1,
        "ByteOffset": 0,
        "ByteMask": 1,
        "FieldMask": 255,
        "BoolSize": 1,
        "bIsNativeBool": true
      },
      {
        "Type": "FloatProperty",
        "Name": "CallFunc_SkillRangeModifier_ModifyResult_1",
        "Flags": "RF_Public",
        "ElementSize": 4
      },
      {
        "Type": "StructProperty",
        "Name": "CallFunc_MakeVector_ReturnValue",
        "Flags": "RF_Public",
        "ElementSize": 12,
        "Struct": {
          "ObjectName": "ScriptStruct'Vector'",
          "ObjectPath": "/Script/CoreUObject"
        }
      },
      {
        "Type": "IntProperty",
        "Name": "___int_Variable",
        "Flags": "RF_Public",
        "ElementSize": 4
      },
      {
        "Type": "IntProperty",
        "Name": "CallFunc_Add_IntInt_ReturnValue_3",
        "Flags": "RF_Public",
        "ElementSize": 4
      },
      {
        "Type": "ArrayProperty",
        "Name": "K2Node_MakeArray_Array",
        "Flags": "RF_Public",
        "ElementSize": 16,
        "PropertyFlags": "ConstParm | ReferenceParm",
        "Inner": {
          "Type": "IntProperty",
          "Name": "K2Node_MakeArray_Array",
          "Flags": "RF_Public",
          "ElementSize": 4
        }
      },
      {
        "Type": "InterfaceProperty",
        "Name": "CallFunc_ExecuteSkillEffects_PreTarget_CastInput",
        "Flags": "RF_Public",
        "ElementSize": 16,
        "PropertyFlags": "ConstParm | UObjectWrapper",
        "InterfaceClass": {
          "ObjectName": "Class'EffectSourceInterface'",
          "ObjectPath": "/Script/EM"
        }
      },
      {
        "Type": "InterfaceProperty",
        "Name": "CallFunc_ExecuteSkillEffects_SkillLevelSource_CastInput",
        "Flags": "RF_Public",
        "ElementSize": 16,
        "PropertyFlags": "ConstParm | UObjectWrapper",
        "InterfaceClass": {
          "ObjectName": "Class'SkillLevelInterface'",
          "ObjectPath": "/Script/EM"
        }
      },
      {
        "Type": "IntProperty",
        "Name": "CallFunc_Add_IntInt_ReturnValue_4",
        "Flags": "RF_Public",
        "ElementSize": 4
      },
      {
        "Type": "ArrayProperty",
        "Name": "K2Node_MakeArray_Array_1",
        "Flags": "RF_Public",
        "ElementSize": 16,
        "PropertyFlags": "ConstParm | ReferenceParm",
        "Inner": {
          "Type": "IntProperty",
          "Name": "K2Node_MakeArray_Array_1",
          "Flags": "RF_Public",
          "ElementSize": 4
        }
      },
      {
        "Type": "ObjectProperty",
        "Name": "CallFunc_Array_Get_Item_2",
        "Flags": "RF_Public",
        "ElementSize": 8,
        "PropertyClass": {
          "ObjectName": "Class'NiagaraSystem'",
          "ObjectPath": "/Script/Niagara"
        }
      },
      {
        "Type": "InterfaceProperty",
        "Name": "CallFunc_ExecuteSkillEffects_PreTarget_CastInput_1",
        "Flags": "RF_Public",
        "ElementSize": 16,
        "PropertyFlags": "ConstParm | UObjectWrapper",
        "InterfaceClass": {
          "ObjectName": "Class'EffectSourceInterface'",
          "ObjectPath": "/Script/EM"
        }
      },
      {
        "Type": "InterfaceProperty",
        "Name": "CallFunc_ExecuteSkillEffects_SkillLevelSource_CastInput_1",
        "Flags": "RF_Public",
        "ElementSize": 16,
        "PropertyFlags": "ConstParm | UObjectWrapper",
        "InterfaceClass": {
          "ObjectName": "Class'SkillLevelInterface'",
          "ObjectPath": "/Script/EM"
        }
      },
      {
        "Type": "StructProperty",
        "Name": "K2Node_CustomEvent_Location",
        "Flags": "RF_Public",
        "ElementSize": 12,
        "Struct": {
          "ObjectName": "ScriptStruct'Vector'",
          "ObjectPath": "/Script/CoreUObject"
        }
      },
      {
        "Type": "StructProperty",
        "Name": "K2Node_CustomEvent_Rotation",
        "Flags": "RF_Public",
        "ElementSize": 12,
        "Struct": {
          "ObjectName": "ScriptStruct'Rotator'",
          "ObjectPath": "/Script/CoreUObject"
        }
      },
      {
        "Type": "StructProperty",
        "Name": "CallFunc_K2_SetActorLocationAndRotation_SweepHitResult",
        "Flags": "RF_Public",
        "ElementSize": 144,
        "PropertyFlags": "ContainsInstancedReference",
        "Struct": {
          "ObjectName": "ScriptStruct'HitResult'",
          "ObjectPath": "/Script/Engine"
        }
      },
      {
        "Type": "BoolProperty",
        "Name": "CallFunc_K2_SetActorLocationAndRotation_ReturnValue",
        "Flags": "RF_Public",
        "ElementSize": 1,
        "FieldSize": 1,
        "ByteOffset": 0,
        "ByteMask": 1,
        "FieldMask": 255,
        "BoolSize": 1,
        "bIsNativeBool": true
      },
      {
        "Type": "DelegateProperty",
        "Name": "K2Node_CreateDelegate_OutputDelegate_1",
        "Flags": "RF_Public",
        "ElementSize": 20,
        "SignatureFunction": {
          "ObjectName": "DelegateFunction'TimerDynamicDelegate__DelegateSignature'",
          "ObjectPath": "/Script/Engine"
        }
      },
      {
        "Type": "InterfaceProperty",
        "Name": "CallFunc_K2_SetTimerDelegate_Combat_OwnerActor_CastInput",
        "Flags": "RF_Public",
        "ElementSize": 16,
        "PropertyFlags": "ConstParm | UObjectWrapper",
        "InterfaceClass": {
          "ObjectName": "Class'TimerManagerInterface'",
          "ObjectPath": "/Script/EM"
        }
      },
      {
        "Type": "StructProperty",
        "Name": "CallFunc_K2_SetTimerDelegate_Combat_ReturnValue",
        "Flags": "RF_Public",
        "ElementSize": 24,
        "Struct": {
          "ObjectName": "ScriptStruct'CombatTimerHandle'",
          "ObjectPath": "/Script/EM"
        }
      },
      {
        "Type": "ObjectProperty",
        "Name": "CallFunc_SpawnSystemAtLocation_ReturnValue",
        "Flags": "RF_Public",
        "ElementSize": 8,
        "PropertyFlags": "InstancedReference",
        "PropertyClass": {
          "ObjectName": "Class'NiagaraComponent'",
          "ObjectPath": "/Script/Niagara"
        }
      },
      {
        "Type": "ObjectProperty",
        "Name": "CallFunc_SpawnSystemAttached_ReturnValue",
        "Flags": "RF_Public",
        "ElementSize": 8,
        "PropertyFlags": "InstancedReference",
        "PropertyClass": {
          "ObjectName": "Class'NiagaraComponent'",
          "ObjectPath": "/Script/Niagara"
        }
      },
      {
        "Type": "BoolProperty",
        "Name": "CallFunc_IsValid_ReturnValue_8",
        "Flags": "RF_Public",
        "ElementSize": 1,
        "FieldSize": 1,
        "ByteOffset": 0,
        "ByteMask": 1,
        "FieldMask": 255,
        "BoolSize": 1,
        "bIsNativeBool": true
      },
      {
        "Type": "BoolProperty",
        "Name": "CallFunc_IsValid_ReturnValue_9",
        "Flags": "RF_Public",
        "ElementSize": 1,
        "FieldSize": 1,
        "ByteOffset": 0,
        "ByteMask": 1,
        "FieldMask": 255,
        "BoolSize": 1,
        "bIsNativeBool": true
      },
      {
        "Type": "InterfaceProperty",
        "Name": "CallFunc_K2_SetTimerDelegate_Combat_OwnerActor_CastInput_1",
        "Flags": "RF_Public",
        "ElementSize": 16,
        "PropertyFlags": "ConstParm | UObjectWrapper",
        "InterfaceClass": {
          "ObjectName": "Class'TimerManagerInterface'",
          "ObjectPath": "/Script/EM"
        }
      },
      {
        "Type": "StructProperty",
        "Name": "CallFunc_K2_SetTimerDelegate_Combat_ReturnValue_1",
        "Flags": "RF_Public",
        "ElementSize": 24,
        "Struct": {
          "ObjectName": "ScriptStruct'CombatTimerHandle'",
          "ObjectPath": "/Script/EM"
        }
      },
      {
        "Type": "FloatProperty",
        "Name": "K2Node_CustomEvent_NewTime",
        "Flags": "RF_Public",
        "ElementSize": 4
      },
      {
        "Type": "ByteProperty",
        "Name": "K2Node_Event_EndPlayReason",
        "Flags": "RF_Public",
        "ElementSize": 1,
        "Enum": {
          "ObjectName": "Enum'EEndPlayReason'",
          "ObjectPath": "/Script/Engine"
        }
      },
      {
        "Type": "StructProperty",
        "Name": "CallFunc_K2_SetActorLocationAndRotation_SweepHitResult_1",
        "Flags": "RF_Public",
        "ElementSize": 144,
        "PropertyFlags": "ContainsInstancedReference",
        "Struct": {
          "ObjectName": "ScriptStruct'HitResult'",
          "ObjectPath": "/Script/Engine"
        }
      },
      {
        "Type": "BoolProperty",
        "Name": "CallFunc_K2_SetActorLocationAndRotation_ReturnValue_1",
        "Flags": "RF_Public",
        "ElementSize": 1,
        "FieldSize": 1,
        "ByteOffset": 0,
        "ByteMask": 1,
        "FieldMask": 255,
        "BoolSize": 1,
        "bIsNativeBool": true
      },
      {
        "Type": "StructProperty",
        "Name": "CallFunc_GetSocketTransform_ReturnValue_3",
        "Flags": "RF_Public",
        "ElementSize": 48,
        "Struct": {
          "ObjectName": "ScriptStruct'Transform'",
          "ObjectPath": "/Script/CoreUObject"
        }
      },
      {
        "Type": "StructProperty",
        "Name": "CallFunc_BreakTransform_Location_2",
        "Flags": "RF_Public",
        "ElementSize": 12,
        "Struct": {
          "ObjectName": "ScriptStruct'Vector'",
          "ObjectPath": "/Script/CoreUObject"
        }
      },
      {
        "Type": "StructProperty",
        "Name": "CallFunc_BreakTransform_Rotation_2",
        "Flags": "RF_Public",
        "ElementSize": 12,
        "Struct": {
          "ObjectName": "ScriptStruct'Rotator'",
          "ObjectPath": "/Script/CoreUObject"
        }
      },
      {
        "Type": "StructProperty",
        "Name": "CallFunc_BreakTransform_Scale_2",
        "Flags": "RF_Public",
        "ElementSize": 12,
        "Struct": {
          "ObjectName": "ScriptStruct'Vector'",
          "ObjectPath": "/Script/CoreUObject"
        }
      },
      {
        "Type": "StructProperty",
        "Name": "CallFunc_K2_SetWorldLocationAndRotation_SweepHitResult",
        "Flags": "RF_Public",
        "ElementSize": 144,
        "PropertyFlags": "ContainsInstancedReference",
        "Struct": {
          "ObjectName": "ScriptStruct'HitResult'",
          "ObjectPath": "/Script/Engine"
        }
      }
    ],
    "FunctionFlags": "FUNC_Final | FUNC_UbergraphFunction | FUNC_HasDefaults"
  },
  {
    "Type": "Function",
    "Name": "OnSummonDead",
    "Outer": "BP_Feina_Summon_C",
    "Class": "UScriptClass'Function'",
    "Flags": "RF_Public | RF_WasLoaded | RF_LoadCompleted",
    "SuperStruct": {
      "ObjectName": "Function'MonsterCharacter:OnSummonDead'",
      "ObjectPath": "/Script/EM"
    },
    "FunctionFlags": "FUNC_Event | FUNC_Public | FUNC_BlueprintEvent"
  },
  {
    "Type": "Function",
    "Name": "ReceiveEndPlay",
    "Outer": "BP_Feina_Summon_C",
    "Class": "UScriptClass'Function'",
    "Flags": "RF_Public | RF_WasLoaded | RF_LoadCompleted",
    "SuperStruct": {
      "ObjectName": "Function'Actor:ReceiveEndPlay'",
      "ObjectPath": "/Script/Engine"
    },
    "ChildProperties": [
      {
        "Type": "ByteProperty",
        "Name": "EndPlayReason",
        "Flags": "RF_Public",
        "ElementSize": 1,
        "PropertyFlags": "BlueprintVisible | BlueprintReadOnly | Parm",
        "Enum": {
          "ObjectName": "Enum'EEndPlayReason'",
          "ObjectPath": "/Script/Engine"
        }
      }
    ],
    "FunctionFlags": "FUNC_Event | FUNC_Protected | FUNC_BlueprintEvent"
  },
  {
    "Type": "Function",
    "Name": "ResetTimer",
    "Outer": "BP_Feina_Summon_C",
    "Class": "UScriptClass'Function'",
    "Flags": "RF_Public | RF_WasLoaded | RF_LoadCompleted",
    "ChildProperties": [
      {
        "Type": "FloatProperty",
        "Name": "NewTime",
        "Flags": "RF_Public",
        "ElementSize": 4,
        "PropertyFlags": "BlueprintVisible | BlueprintReadOnly | Parm"
      }
    ],
    "FunctionFlags": "FUNC_BlueprintCallable | FUNC_BlueprintEvent"
  },
  {
    "Type": "Function",
    "Name": "SetSummonTransform",
    "Outer": "BP_Feina_Summon_C",
    "Class": "UScriptClass'Function'",
    "Flags": "RF_Public | RF_WasLoaded | RF_LoadCompleted",
    "ChildProperties": [
      {
        "Type": "StructProperty",
        "Name": "Location",
        "Flags": "RF_Public",
        "ElementSize": 12,
        "PropertyFlags": "BlueprintVisible | BlueprintReadOnly | Parm",
        "Struct": {
          "ObjectName": "ScriptStruct'Vector'",
          "ObjectPath": "/Script/CoreUObject"
        }
      },
      {
        "Type": "StructProperty",
        "Name": "Rotation",
        "Flags": "RF_Public",
        "ElementSize": 12,
        "PropertyFlags": "BlueprintVisible | BlueprintReadOnly | Parm",
        "Struct": {
          "ObjectName": "ScriptStruct'Rotator'",
          "ObjectPath": "/Script/CoreUObject"
        }
      }
    ],
    "FunctionFlags": "FUNC_Net | FUNC_NetMulticast | FUNC_BlueprintCallable | FUNC_BlueprintEvent"
  },
  {
    "Type": "Function",
    "Name": "ClientBeginPlay",
    "Outer": "BP_Feina_Summon_C",
    "Class": "UScriptClass'Function'",
    "Flags": "RF_Public | RF_WasLoaded | RF_LoadCompleted",
    "SuperStruct": {
      "ObjectName": "Function'CharacterBase:ClientBeginPlay'",
      "ObjectPath": "/Script/EM"
    },
    "FunctionFlags": "FUNC_Event | FUNC_Public | FUNC_BlueprintEvent"
  },
  {
    "Type": "Function",
    "Name": "PhantomSummon",
    "Outer": "BP_Feina_Summon_C",
    "Class": "UScriptClass'Function'",
    "Flags": "RF_Public | RF_WasLoaded | RF_LoadCompleted",
    "FunctionFlags": "FUNC_BlueprintCallable | FUNC_BlueprintEvent"
  },
  {
    "Type": "Function",
    "Name": "PlaySkill1Anim",
    "Outer": "BP_Feina_Summon_C",
    "Class": "UScriptClass'Function'",
    "Flags": "RF_Public | RF_WasLoaded | RF_LoadCompleted",
    "FunctionFlags": "FUNC_Net | FUNC_NetMulticast | FUNC_BlueprintCallable | FUNC_BlueprintEvent"
  },
  {
    "Type": "Function",
    "Name": "SwitchSummon",
    "Outer": "BP_Feina_Summon_C",
    "Class": "UScriptClass'Function'",
    "Flags": "RF_Public | RF_WasLoaded | RF_LoadCompleted",
    "ChildProperties": [
      {
        "Type": "BoolProperty",
        "Name": "Reset",
        "Flags": "RF_Public",
        "ElementSize": 1,
        "PropertyFlags": "BlueprintVisible | BlueprintReadOnly | Parm",
        "FieldSize": 1,
        "ByteOffset": 0,
        "ByteMask": 1,
        "FieldMask": 255,
        "BoolSize": 1,
        "bIsNativeBool": true
      }
    ],
    "FunctionFlags": "FUNC_BlueprintCallable | FUNC_BlueprintEvent"
  },
  {
    "Type": "Function",
    "Name": "SetSummonAssets",
    "Outer": "BP_Feina_Summon_C",
    "Class": "UScriptClass'Function'",
    "Flags": "RF_Public | RF_WasLoaded | RF_LoadCompleted",
    "FunctionFlags": "FUNC_Net | FUNC_NetMulticast | FUNC_BlueprintCallable | FUNC_BlueprintEvent"
  },
  {
    "Type": "Function",
    "Name": "ServerBeginPlay",
    "Outer": "BP_Feina_Summon_C",
    "Class": "UScriptClass'Function'",
    "Flags": "RF_Public | RF_WasLoaded | RF_LoadCompleted",
    "SuperStruct": {
      "ObjectName": "Function'CharacterBase:ServerBeginPlay'",
      "ObjectPath": "/Script/EM"
    },
    "FunctionFlags": "FUNC_Event | FUNC_Public | FUNC_BlueprintEvent"
  },
  {
    "Type": "Function",
    "Name": "AddPassiveBuff",
    "Outer": "BP_Feina_Summon_C",
    "Class": "UScriptClass'Function'",
    "Flags": "RF_Public | RF_WasLoaded | RF_LoadCompleted",
    "FunctionFlags": "FUNC_BlueprintCallable | FUNC_BlueprintEvent"
  },
  {
    "Type": "Function",
    "Name": "SummonSwitchSkill",
    "Outer": "BP_Feina_Summon_C",
    "Class": "UScriptClass'Function'",
    "Flags": "RF_Public | RF_WasLoaded | RF_LoadCompleted",
    "FunctionFlags": "FUNC_BlueprintCallable | FUNC_BlueprintEvent"
  },
  {
    "Type": "Function",
    "Name": "ReceiveBeginPlay",
    "Outer": "BP_Feina_Summon_C",
    "Class": "UScriptClass'Function'",
    "Super": {
      "ObjectName": "Function'BP_MonsterCharacter_C:ReceiveBeginPlay'",
      "ObjectPath": "EM/Content/BluePrints/Char/BP_Monsters/BP_MonsterCharacter.20"
    },
    "Flags": "RF_Public | RF_WasLoaded | RF_LoadCompleted",
    "SuperStruct": {
      "ObjectName": "Function'BP_MonsterCharacter_C:ReceiveBeginPlay'",
      "ObjectPath": "EM/Content/BluePrints/Char/BP_Monsters/BP_MonsterCharacter.20"
    },
    "FunctionFlags": "FUNC_Event | FUNC_Protected | FUNC_BlueprintEvent"
  },
  {
    "Type": "Function",
    "Name": "SetSummon",
    "Outer": "BP_Feina_Summon_C",
    "Class": "UScriptClass'Function'",
    "Flags": "RF_Public | RF_WasLoaded | RF_LoadCompleted",
    "FunctionFlags": "FUNC_Public | FUNC_BlueprintCallable | FUNC_BlueprintEvent"
  },
  {
    "Type": "Function",
    "Name": "IsSummonSwitch",
    "Outer": "BP_Feina_Summon_C",
    "Class": "UScriptClass'Function'",
    "Flags": "RF_Public | RF_WasLoaded | RF_LoadCompleted",
    "ChildProperties": [
      {
        "Type": "BoolProperty",
        "Name": "CallFunc_EqualEqual_IntInt_ReturnValue",
        "Flags": "RF_Public",
        "ElementSize": 1,
        "FieldSize": 1,
        "ByteOffset": 0,
        "ByteMask": 1,
        "FieldMask": 255,
        "BoolSize": 1,
        "bIsNativeBool": true
      }
    ],
    "FunctionFlags": "FUNC_Public | FUNC_BlueprintCallable | FUNC_BlueprintEvent"
  },
  {
    "Type": "Function",
    "Name": "PlaySe",
    "Outer": "BP_Feina_Summon_C",
    "Class": "UScriptClass'Function'",
    "Flags": "RF_Public | RF_WasLoaded | RF_LoadCompleted",
    "ChildProperties": [
      {
        "Type": "IntProperty",
        "Name": "SummonID",
        "Flags": "RF_Public",
        "ElementSize": 4,
        "PropertyFlags": "BlueprintVisible | BlueprintReadOnly | Parm"
      },
      {
        "Type": "ObjectProperty",
        "Name": "Niagara",
        "Flags": "RF_Public",
        "ElementSize": 8,
        "PropertyFlags": "BlueprintVisible | BlueprintReadOnly | Parm | InstancedReference",
        "PropertyClass": {
          "ObjectName": "Class'NiagaraComponent'",
          "ObjectPath": "/Script/Niagara"
        }
      },
      {
        "Type": "StrProperty",
        "Name": "CallFunc_Conv_IntToString_ReturnValue",
        "Flags": "RF_Public",
        "ElementSize": 16
      },
      {
        "Type": "BoolProperty",
        "Name": "CallFunc_IsStandAloneOrClient_ReturnValue",
        "Flags": "RF_Public",
        "ElementSize": 1,
        "PropertyFlags": "ConstParm",
        "FieldSize": 1,
        "ByteOffset": 0,
        "ByteMask": 1,
        "FieldMask": 255,
        "BoolSize": 1,
        "bIsNativeBool": true
      },
      {
        "Type": "BoolProperty",
        "Name": "K2Node_SwitchString_CmpSuccess",
        "Flags": "RF_Public",
        "ElementSize": 1,
        "FieldSize": 1,
        "ByteOffset": 0,
        "ByteMask": 1,
        "FieldMask": 255,
        "BoolSize": 1,
        "bIsNativeBool": true
      },
      {
        "Type": "MapProperty",
        "Name": "K2Node_MakeMap_Map",
        "Flags": "RF_Public",
        "ElementSize": 80,
        "PropertyFlags": "ConstParm",
        "KeyProp": {
          "Type": "StrProperty",
          "Name": "K2Node_MakeMap_Map",
          "Flags": "RF_Public",
          "ElementSize": 16
        },
        "ValueProp": {
          "Type": "FloatProperty",
          "Name": "K2Node_MakeMap_Map_Value",
          "Flags": "RF_Public",
          "ElementSize": 4
        }
      },
      {
        "Type": "MapProperty",
        "Name": "K2Node_MakeMap_Map_1",
        "Flags": "RF_Public",
        "ElementSize": 80,
        "PropertyFlags": "ConstParm",
        "KeyProp": {
          "Type": "StrProperty",
          "Name": "K2Node_MakeMap_Map_1",
          "Flags": "RF_Public",
          "ElementSize": 16
        },
        "ValueProp": {
          "Type": "FloatProperty",
          "Name": "K2Node_MakeMap_Map_Value",
          "Flags": "RF_Public",
          "ElementSize": 4
        }
      },
      {
        "Type": "ObjectProperty",
        "Name": "CallFunc_GetClientAudioManager_AudioManager",
        "Flags": "RF_Public",
        "ElementSize": 8,
        "PropertyClass": {
          "ObjectName": "BlueprintGeneratedClass'BP_AudioManager_C'",
          "ObjectPath": "EM/Content/BluePrints/Managers/BP_AudioManager.10"
        }
      },
      {
        "Type": "InterfaceProperty",
        "Name": "CallFunc_GetCreator_Target_CastInput",
        "Flags": "RF_Public",
        "ElementSize": 16,
        "PropertyFlags": "ConstParm | UObjectWrapper",
        "InterfaceClass": {
          "ObjectName": "Class'EffectSourceInterface'",
          "ObjectPath": "/Script/EM"
        }
      },
      {
        "Type": "InterfaceProperty",
        "Name": "CallFunc_GetCreator_ReturnValue",
        "Flags": "RF_Public",
        "ElementSize": 16,
        "PropertyFlags": "UObjectWrapper",
        "InterfaceClass": {
          "ObjectName": "Class'EffectSourceInterface'",
          "ObjectPath": "/Script/EM"
        }
      },
      {
        "Type": "ObjectProperty",
        "Name": "CallFunc_Conv_InterfaceToObject_ReturnValue",
        "Flags": "RF_Public",
        "ElementSize": 8,
        "PropertyClass": {
          "ObjectName": "Class'Object'",
          "ObjectPath": "/Script/CoreUObject"
        }
      },
      {
        "Type": "ObjectProperty",
        "Name": "CallFunc_GetClientAudioManager_AudioManager_1",
        "Flags": "RF_Public",
        "ElementSize": 8,
        "PropertyClass": {
          "ObjectName": "BlueprintGeneratedClass'BP_AudioManager_C'",
          "ObjectPath": "EM/Content/BluePrints/Managers/BP_AudioManager.10"
        }
      },
      {
        "Type": "InterfaceProperty",
        "Name": "CallFunc_GetCreator_Target_CastInput_1",
        "Flags": "RF_Public",
        "ElementSize": 16,
        "PropertyFlags": "ConstParm | UObjectWrapper",
        "InterfaceClass": {
          "ObjectName": "Class'EffectSourceInterface'",
          "ObjectPath": "/Script/EM"
        }
      },
      {
        "Type": "InterfaceProperty",
        "Name": "CallFunc_GetCreator_ReturnValue_1",
        "Flags": "RF_Public",
        "ElementSize": 16,
        "PropertyFlags": "UObjectWrapper",
        "InterfaceClass": {
          "ObjectName": "Class'EffectSourceInterface'",
          "ObjectPath": "/Script/EM"
        }
      },
      {
        "Type": "ObjectProperty",
        "Name": "CallFunc_Conv_InterfaceToObject_ReturnValue_1",
        "Flags": "RF_Public",
        "ElementSize": 8,
        "PropertyClass": {
          "ObjectName": "Class'Object'",
          "ObjectPath": "/Script/CoreUObject"
        }
      }
    ],
    "FunctionFlags": "FUNC_Public | FUNC_HasDefaults | FUNC_BlueprintCallable | FUNC_BlueprintEvent"
  },
  {
    "Type": "BlueprintGeneratedClass",
    "Name": "BP_Feina_Summon_C",
    "Class": "UScriptClass'BlueprintGeneratedClass'",
    "Super": {
      "ObjectName": "BlueprintGeneratedClass'BP_MonsterCharacter_C'",
      "ObjectPath": "EM/Content/BluePrints/Char/BP_Monsters/BP_MonsterCharacter.42"
    },
    "Flags": "RF_Public | RF_Transactional | RF_WasLoaded | RF_LoadCompleted",
    "Properties": {
      "NumReplicatedProperties": 3,
      "SimpleConstructionScript": {
        "ObjectName": "SimpleConstructionScript'BP_Feina_Summon_C:SimpleConstructionScript_0'",
        "ObjectPath": "EM/Content/AssetDesign/Char/Player/Feina/BP_Feina_Summon.53"
      },
      "InheritableComponentHandler": {
        "ObjectName": "InheritableComponentHandler'BP_Feina_Summon_C:InheritableComponentHandler'",
        "ObjectPath": "EM/Content/AssetDesign/Char/Player/Feina/BP_Feina_Summon.37"
      },
      "UberGraphFunction": {
        "ObjectName": "Function'BP_Feina_Summon_C:ExecuteUbergraph_BP_Feina_Summon'",
        "ObjectPath": "EM/Content/AssetDesign/Char/Player/Feina/BP_Feina_Summon.1"
      }
    },
    "SuperStruct": {
      "ObjectName": "BlueprintGeneratedClass'BP_MonsterCharacter_C'",
      "ObjectPath": "EM/Content/BluePrints/Char/BP_Monsters/BP_MonsterCharacter.42"
    },
    "Children": [
      {
        "ObjectName": "Function'BP_Feina_Summon_C:PlaySe'",
        "ObjectPath": "EM/Content/AssetDesign/Char/Player/Feina/BP_Feina_Summon.17"
      },
      {
        "ObjectName": "Function'BP_Feina_Summon_C:IsSummonSwitch'",
        "ObjectPath": "EM/Content/AssetDesign/Char/Player/Feina/BP_Feina_Summon.16"
      },
      {
        "ObjectName": "Function'BP_Feina_Summon_C:SetSummon'",
        "ObjectPath": "EM/Content/AssetDesign/Char/Player/Feina/BP_Feina_Summon.15"
      },
      {
        "ObjectName": "Function'BP_Feina_Summon_C:ReceiveBeginPlay'",
        "ObjectPath": "EM/Content/AssetDesign/Char/Player/Feina/BP_Feina_Summon.14"
      },
      {
        "ObjectName": "Function'BP_Feina_Summon_C:SummonSwitchSkill'",
        "ObjectPath": "EM/Content/AssetDesign/Char/Player/Feina/BP_Feina_Summon.13"
      },
      {
        "ObjectName": "Function'BP_Feina_Summon_C:AddPassiveBuff'",
        "ObjectPath": "EM/Content/AssetDesign/Char/Player/Feina/BP_Feina_Summon.12"
      },
      {
        "ObjectName": "Function'BP_Feina_Summon_C:ServerBeginPlay'",
        "ObjectPath": "EM/Content/AssetDesign/Char/Player/Feina/BP_Feina_Summon.11"
      },
      {
        "ObjectName": "Function'BP_Feina_Summon_C:SetSummonAssets'",
        "ObjectPath": "EM/Content/AssetDesign/Char/Player/Feina/BP_Feina_Summon.10"
      },
      {
        "ObjectName": "Function'BP_Feina_Summon_C:SwitchSummon'",
        "ObjectPath": "EM/Content/AssetDesign/Char/Player/Feina/BP_Feina_Summon.9"
      },
      {
        "ObjectName": "Function'BP_Feina_Summon_C:PlaySkill1Anim'",
        "ObjectPath": "EM/Content/AssetDesign/Char/Player/Feina/BP_Feina_Summon.8"
      },
      {
        "ObjectName": "Function'BP_Feina_Summon_C:PhantomSummon'",
        "ObjectPath": "EM/Content/AssetDesign/Char/Player/Feina/BP_Feina_Summon.7"
      },
      {
        "ObjectName": "Function'BP_Feina_Summon_C:ClientBeginPlay'",
        "ObjectPath": "EM/Content/AssetDesign/Char/Player/Feina/BP_Feina_Summon.6"
      },
      {
        "ObjectName": "Function'BP_Feina_Summon_C:SetSummonTransform'",
        "ObjectPath": "EM/Content/AssetDesign/Char/Player/Feina/BP_Feina_Summon.5"
      },
      {
        "ObjectName": "Function'BP_Feina_Summon_C:ResetTimer'",
        "ObjectPath": "EM/Content/AssetDesign/Char/Player/Feina/BP_Feina_Summon.4"
      },
      {
        "ObjectName": "Function'BP_Feina_Summon_C:ReceiveEndPlay'",
        "ObjectPath": "EM/Content/AssetDesign/Char/Player/Feina/BP_Feina_Summon.3"
      },
      {
        "ObjectName": "Function'BP_Feina_Summon_C:OnSummonDead'",
        "ObjectPath": "EM/Content/AssetDesign/Char/Player/Feina/BP_Feina_Summon.2"
      },
      {
        "ObjectName": "Function'BP_Feina_Summon_C:ExecuteUbergraph_BP_Feina_Summon'",
        "ObjectPath": "EM/Content/AssetDesign/Char/Player/Feina/BP_Feina_Summon.1"
      },
      {
        "ObjectName": "Function'BP_Feina_Summon_C:SummonSwitch__DelegateSignature'",
        "ObjectPath": "EM/Content/AssetDesign/Char/Player/Feina/BP_Feina_Summon.0"
      }
    ],
    "ChildProperties": [
      {
        "Type": "StructProperty",
        "Name": "UberGraphFrame",
        "Flags": "RF_Public | RF_LoadCompleted",
        "ElementSize": 16,
        "PropertyFlags": "Transient | DuplicateTransient",
        "Struct": {
          "ObjectName": "ScriptStruct'PointerToUberGraphFrame'",
          "ObjectPath": "/Script/Engine"
        }
      },
      {
        "Type": "IntProperty",
        "Name": "SummonID",
        "Flags": "RF_Public | RF_LoadCompleted",
        "ElementSize": 4,
        "PropertyFlags": "Edit | BlueprintVisible | Net | DisableEditOnInstance",
        "RepIndex": 75
      },
      {
        "Type": "IntProperty",
        "Name": "NewSumID",
        "Flags": "RF_Public | RF_LoadCompleted",
        "ElementSize": 4,
        "PropertyFlags": "Edit | BlueprintVisible | Net | DisableEditOnInstance",
        "RepIndex": 76
      },
      {
        "Type": "ObjectProperty",
        "Name": "SummonCreature",
        "Flags": "RF_Public | RF_LoadCompleted",
        "ElementSize": 8,
        "PropertyFlags": "Edit | BlueprintVisible | DisableEditOnTemplate | DisableEditOnInstance",
        "PropertyClass": {
          "ObjectName": "BlueprintGeneratedClass'BP_EffectCreature_Feina_Summon_C'",
          "ObjectPath": "EM/Content/BluePrints/Combat/EffectCreature/Skill/BP_EffectCreature_Feina_Summon.7"
        }
      },
      {
        "Type": "ArrayProperty",
        "Name": "FxColor",
        "Flags": "RF_Public | RF_LoadCompleted",
        "ElementSize": 16,
        "PropertyFlags": "Edit | BlueprintVisible | DisableEditOnInstance",
        "Inner": {
          "Type": "StructProperty",
          "Name": "FxColor",
          "Flags": "RF_Public",
          "ElementSize": 16,
          "Struct": {
            "ObjectName": "ScriptStruct'LinearColor'",
            "ObjectPath": "/Script/CoreUObject"
          }
        }
      },
      {
        "Type": "ObjectProperty",
        "Name": "OwnerSkill",
        "Flags": "RF_Public | RF_LoadCompleted",
        "ElementSize": 8,
        "PropertyFlags": "Edit | BlueprintVisible | DisableEditOnInstance",
        "PropertyClass": {
          "ObjectName": "Class'SkillObject'",
          "ObjectPath": "/Script/EM"
        }
      },
      {
        "Type": "MulticastInlineDelegateProperty",
        "Name": "SummonSwitch",
        "Flags": "RF_Public | RF_LoadCompleted",
        "ElementSize": 16,
        "PropertyFlags": "Edit | BlueprintVisible | DisableEditOnInstance | BlueprintAssignable | BlueprintCallable",
        "SignatureFunction": {
          "ObjectName": "Function'BP_Feina_Summon_C:SummonSwitch__DelegateSignature'",
          "ObjectPath": "EM/Content/AssetDesign/Char/Player/Feina/BP_Feina_Summon.0"
        }
      },
      {
        "Type": "BoolProperty",
        "Name": "ResetSumID",
        "Flags": "RF_Public | RF_LoadCompleted",
        "ElementSize": 1,
        "PropertyFlags": "Edit | BlueprintVisible | Net | DisableEditOnInstance",
        "RepIndex": 77,
        "FieldSize": 1,
        "ByteOffset": 0,
        "ByteMask": 1,
        "FieldMask": 255,
        "BoolSize": 1,
        "bIsNativeBool": true
      },
      {
        "Type": "IntProperty",
        "Name": "AISumID",
        "Flags": "RF_Public | RF_LoadCompleted",
        "ElementSize": 4,
        "PropertyFlags": "Edit | BlueprintVisible | DisableEditOnInstance"
      },
      {
        "Type": "BoolProperty",
        "Name": "AISum",
        "Flags": "RF_Public | RF_LoadCompleted",
        "ElementSize": 1,
        "PropertyFlags": "Edit | BlueprintVisible | DisableEditOnInstance",
        "FieldSize": 1,
        "ByteOffset": 0,
        "ByteMask": 1,
        "FieldMask": 255,
        "BoolSize": 1,
        "bIsNativeBool": true
      },
      {
        "Type": "ArrayProperty",
        "Name": "AuraFx",
        "Flags": "RF_Public | RF_LoadCompleted",
        "ElementSize": 16,
        "PropertyFlags": "Edit | BlueprintVisible | DisableEditOnInstance",
        "Inner": {
          "Type": "ObjectProperty",
          "Name": "AuraFx",
          "Flags": "RF_Public",
          "ElementSize": 8,
          "PropertyClass": {
            "ObjectName": "Class'NiagaraSystem'",
            "ObjectPath": "/Script/Niagara"
          }
        }
      },
      {
        "Type": "ObjectProperty",
        "Name": "CurrentAura",
        "Flags": "RF_Public | RF_LoadCompleted",
        "ElementSize": 8,
        "PropertyFlags": "Edit | BlueprintVisible | DisableEditOnInstance | InstancedReference",
        "PropertyClass": {
          "ObjectName": "Class'NiagaraComponent'",
          "ObjectPath": "/Script/Niagara"
        }
      },
      {
        "Type": "ObjectProperty",
        "Name": "BuffFx",
        "Flags": "RF_Public | RF_LoadCompleted",
        "ElementSize": 8,
        "PropertyFlags": "Edit | BlueprintVisible | DisableEditOnInstance | InstancedReference",
        "PropertyClass": {
          "ObjectName": "Class'NiagaraComponent'",
          "ObjectPath": "/Script/Niagara"
        }
      },
      {
        "Type": "FloatProperty",
        "Name": "BuffIndex",
        "Flags": "RF_Public | RF_LoadCompleted",
        "ElementSize": 4,
        "PropertyFlags": "Edit | BlueprintVisible | DisableEditOnInstance"
      },
      {
        "Type": "ArrayProperty",
        "Name": "AttackFx",
        "Flags": "RF_Public | RF_LoadCompleted",
        "ElementSize": 16,
        "PropertyFlags": "Edit | BlueprintVisible | DisableEditOnInstance",
        "Inner": {
          "Type": "ObjectProperty",
          "Name": "AttackFx",
          "Flags": "RF_Public",
          "ElementSize": 8,
          "PropertyClass": {
            "ObjectName": "Class'NiagaraSystem'",
            "ObjectPath": "/Script/Niagara"
          }
        }
      },
      {
        "Type": "IntProperty",
        "Name": "BonusBuffID",
        "Flags": "RF_Public | RF_LoadCompleted",
        "ElementSize": 4,
        "PropertyFlags": "Edit | BlueprintVisible | DisableEditOnInstance"
      },
      {
        "Type": "FloatProperty",
        "Name": "FxDelay",
        "Flags": "RF_Public | RF_LoadCompleted",
        "ElementSize": 4,
        "PropertyFlags": "Edit | BlueprintVisible | DisableEditOnInstance"
      },
      {
        "Type": "IntProperty",
        "Name": "SeId",
        "Flags": "RF_Public | RF_LoadCompleted",
        "ElementSize": 4,
        "PropertyFlags": "Edit | BlueprintVisible | DisableEditOnInstance"
      },
      {
        "Type": "FloatProperty",
        "Name": "LoopTime",
        "Flags": "RF_Public | RF_LoadCompleted",
        "ElementSize": 4,
        "PropertyFlags": "Edit | BlueprintVisible | DisableEditOnInstance"
      }
    ],
    "FuncMap": {
      "SummonSwitch__DelegateSignature": {
        "ObjectName": "Function'BP_Feina_Summon_C:SummonSwitch__DelegateSignature'",
        "ObjectPath": "EM/Content/AssetDesign/Char/Player/Feina/BP_Feina_Summon.0"
      },
      "ExecuteUbergraph_BP_Feina_Summon": {
        "ObjectName": "Function'BP_Feina_Summon_C:ExecuteUbergraph_BP_Feina_Summon'",
        "ObjectPath": "EM/Content/AssetDesign/Char/Player/Feina/BP_Feina_Summon.1"
      },
      "OnSummonDead": {
        "ObjectName": "Function'BP_Feina_Summon_C:OnSummonDead'",
        "ObjectPath": "EM/Content/AssetDesign/Char/Player/Feina/BP_Feina_Summon.2"
      },
      "ReceiveEndPlay": {
        "ObjectName": "Function'BP_Feina_Summon_C:ReceiveEndPlay'",
        "ObjectPath": "EM/Content/AssetDesign/Char/Player/Feina/BP_Feina_Summon.3"
      },
      "ResetTimer": {
        "ObjectName": "Function'BP_Feina_Summon_C:ResetTimer'",
        "ObjectPath": "EM/Content/AssetDesign/Char/Player/Feina/BP_Feina_Summon.4"
      },
      "SetSummonTransform": {
        "ObjectName": "Function'BP_Feina_Summon_C:SetSummonTransform'",
        "ObjectPath": "EM/Content/AssetDesign/Char/Player/Feina/BP_Feina_Summon.5"
      },
      "ClientBeginPlay": {
        "ObjectName": "Function'BP_Feina_Summon_C:ClientBeginPlay'",
        "ObjectPath": "EM/Content/AssetDesign/Char/Player/Feina/BP_Feina_Summon.6"
      },
      "PhantomSummon": {
        "ObjectName": "Function'BP_Feina_Summon_C:PhantomSummon'",
        "ObjectPath": "EM/Content/AssetDesign/Char/Player/Feina/BP_Feina_Summon.7"
      },
      "PlaySkill1Anim": {
        "ObjectName": "Function'BP_Feina_Summon_C:PlaySkill1Anim'",
        "ObjectPath": "EM/Content/AssetDesign/Char/Player/Feina/BP_Feina_Summon.8"
      },
      "SwitchSummon": {
        "ObjectName": "Function'BP_Feina_Summon_C:SwitchSummon'",
        "ObjectPath": "EM/Content/AssetDesign/Char/Player/Feina/BP_Feina_Summon.9"
      },
      "SetSummonAssets": {
        "ObjectName": "Function'BP_Feina_Summon_C:SetSummonAssets'",
        "ObjectPath": "EM/Content/AssetDesign/Char/Player/Feina/BP_Feina_Summon.10"
      },
      "ServerBeginPlay": {
        "ObjectName": "Function'BP_Feina_Summon_C:ServerBeginPlay'",
        "ObjectPath": "EM/Content/AssetDesign/Char/Player/Feina/BP_Feina_Summon.11"
      },
      "AddPassiveBuff": {
        "ObjectName": "Function'BP_Feina_Summon_C:AddPassiveBuff'",
        "ObjectPath": "EM/Content/AssetDesign/Char/Player/Feina/BP_Feina_Summon.12"
      },
      "SummonSwitchSkill": {
        "ObjectName": "Function'BP_Feina_Summon_C:SummonSwitchSkill'",
        "ObjectPath": "EM/Content/AssetDesign/Char/Player/Feina/BP_Feina_Summon.13"
      },
      "ReceiveBeginPlay": {
        "ObjectName": "Function'BP_Feina_Summon_C:ReceiveBeginPlay'",
        "ObjectPath": "EM/Content/AssetDesign/Char/Player/Feina/BP_Feina_Summon.14"
      },
      "SetSummon": {
        "ObjectName": "Function'BP_Feina_Summon_C:SetSummon'",
        "ObjectPath": "EM/Content/AssetDesign/Char/Player/Feina/BP_Feina_Summon.15"
      },
      "IsSummonSwitch": {
        "ObjectName": "Function'BP_Feina_Summon_C:IsSummonSwitch'",
        "ObjectPath": "EM/Content/AssetDesign/Char/Player/Feina/BP_Feina_Summon.16"
      },
      "PlaySe": {
        "ObjectName": "Function'BP_Feina_Summon_C:PlaySe'",
        "ObjectPath": "EM/Content/AssetDesign/Char/Player/Feina/BP_Feina_Summon.17"
      }
    },
    "ClassFlags": "CLASS_Config | CLASS_Optional | CLASS_ReplicationDataIsSetUp | CLASS_CompiledFromBlueprint | CLASS_HasInstancedReference",
    "ClassWithin": {
      "ObjectName": "Class'Object'",
      "ObjectPath": "/Script/CoreUObject"
    },
    "ClassConfigName": "Game",
    "bCooked": true,
    "ClassDefaultObject": {
      "ObjectName": "BP_Feina_Summon_C'Default__BP_Feina_Summon_C'",
      "ObjectPath": "EM/Content/AssetDesign/Char/Player/Feina/BP_Feina_Summon.19"
    }
  },
  {
    "Type": "BP_Feina_Summon_C",
    "Name": "Default__BP_Feina_Summon_C",
    "Class": "BlueprintGeneratedClass'EM/Content/AssetDesign/Char/Player/Feina/BP_Feina_Summon.BP_Feina_Summon_C'",
    "Template": {
      "ObjectName": "BP_MonsterCharacter_C'Default__BP_MonsterCharacter_C'",
      "ObjectPath": "EM/Content/BluePrints/Char/BP_Monsters/BP_MonsterCharacter.43"
    },
    "Flags": "RF_Public | RF_ClassDefaultObject | RF_ArchetypeObject | RF_WasLoaded | RF_LoadCompleted",
    "Properties": {
      "UberGraphFrame": {},
      "FxColor": [
        {
          "R": 1.0,
          "G": 6.5,
          "B": 12.0,
          "A": 1.0,
          "Hex": "FFFFFF"
        },
        {
          "R": 12.0,
          "G": 1.2,
          "B": 0.0,
          "A": 1.0,
          "Hex": "FFFF00"
        },
        {
          "R": 10.0,
          "G": 1.35,
          "B": 9.0,
          "A": 1.0,
          "Hex": "FFFFFF"
        },
        {
          "R": 4.5,
          "G": 10.0,
          "B": 0.0,
          "A": 1.0,
          "Hex": "FFFF00"
        }
      ],
      "AuraFx": [
        {
          "ObjectName": "NiagaraSystem'NS_Feina_Skill02_WaterCircle'",
          "ObjectPath": "EM/Content/Asset/Effect/Niagara/Player/Feina/NS_Feina_Skill02_WaterCircle.414"
        },
        {
          "ObjectName": "NiagaraSystem'NS_Feina_Skill02_FireCircle'",
          "ObjectPath": "EM/Content/Asset/Effect/Niagara/Player/Feina/NS_Feina_Skill02_FireCircle.278"
        },
        {
          "ObjectName": "NiagaraSystem'NS_Feina_Skill02_ElectricCircle'",
          "ObjectPath": "EM/Content/Asset/Effect/Niagara/Player/Feina/NS_Feina_Skill02_ElectricCircle.216"
        },
        {
          "ObjectName": "NiagaraSystem'NS_Feina_Skill02_WindCircle'",
          "ObjectPath": "EM/Content/Asset/Effect/Niagara/Player/Feina/NS_Feina_Skill02_WindCircle.306"
        }
      ],
      "BuffIndex": 1.0,
      "AttackFx": [
        {
          "ObjectName": "NiagaraSystem'NS_Feina_Skill02_Sum01Attack'",
          "ObjectPath": "EM/Content/Asset/Effect/Niagara/Player/Feina/NS_Feina_Skill02_Sum01Attack.210"
        },
        {
          "ObjectName": "NiagaraSystem'NS_Feina_Skill02_Sum04Attack'",
          "ObjectPath": "EM/Content/Asset/Effect/Niagara/Player/Feina/NS_Feina_Skill02_Sum04Attack.264"
        },
        {
          "ObjectName": "NiagaraSystem'NS_Feina_Skill02_Sum03Attack'",
          "ObjectPath": "EM/Content/Asset/Effect/Niagara/Player/Feina/NS_Feina_Skill02_Sum03Attack.197"
        },
        {
          "ObjectName": "NiagaraSystem'NS_Feina_Skill02_Sum02Attack'",
          "ObjectPath": "EM/Content/Asset/Effect/Niagara/Player/Feina/NS_Feina_Skill02_Sum02Attack.222"
        }
      ],
      "BonusBuffID": 180121,
      "LoopTime": 2.5,
      "NavLinkJumpComponent": {
        "ObjectName": "NavLinkJumpComponent'Default__BP_Feina_Summon_C:NavLinkJumpComponent'",
        "ObjectPath": "EM/Content/AssetDesign/Char/Player/Feina/BP_Feina_Summon.50"
      },
      "MonDecisionStateComponent": {
        "ObjectName": "MonDecisionStateComponent'Default__BP_Feina_Summon_C:MonDecisionStateComponent'",
        "ObjectPath": "EM/Content/AssetDesign/Char/Player/Feina/BP_Feina_Summon.40"
      },
      "AirWallPenetrateComponent": {
        "ObjectName": "AirWallPenetrateComponent'Default__BP_Feina_Summon_C:AirWallPenetrateComponent'",
        "ObjectPath": "EM/Content/AssetDesign/Char/Player/Feina/BP_Feina_Summon.21"
      },
      "MonAlertComponent": {
        "ObjectName": "MonAlertComponent'Default__BP_Feina_Summon_C:MonAlertComponent'",
        "ObjectPath": "EM/Content/AssetDesign/Char/Player/Feina/BP_Feina_Summon.38"
      },
      "MonEliteComponent": {
        "ObjectName": "MonEliteComponent'Default__BP_Feina_Summon_C:MonEliteComponent'",
        "ObjectPath": "EM/Content/AssetDesign/Char/Player/Feina/BP_Feina_Summon.41"
      },
      "MonUpdateBBComponent": {
        "ObjectName": "MonUpdateBBComponent'Default__BP_Feina_Summon_C:MonUpdateBBComponent'",
        "ObjectPath": "EM/Content/AssetDesign/Char/Player/Feina/BP_Feina_Summon.47"
      },
      "MonExtraVitaminComponent": {
        "ObjectName": "MonExtraVitaminComponent'Default__BP_Feina_Summon_C:MonExtraVitaminComponent'",
        "ObjectPath": "EM/Content/AssetDesign/Char/Player/Feina/BP_Feina_Summon.42"
      },
      "BeAttackTimeline": {
        "ObjectName": "TimelineComponent'Default__BP_Feina_Summon_C:BeAttackTimeline'",
        "ObjectPath": "EM/Content/AssetDesign/Char/Player/Feina/BP_Feina_Summon.54"
      },
      "EQSTestingComponent": {
        "ObjectName": "EQSTestingComponent'Default__BP_Feina_Summon_C:EQSTestingComponent'",
        "ObjectPath": "EM/Content/AssetDesign/Char/Player/Feina/BP_Feina_Summon.36"
      },
      "MonOptimizationComponent": {
        "ObjectName": "MonOptimizationComponent'Default__BP_Feina_Summon_C:MonOptimizationComponent'",
        "ObjectPath": "EM/Content/AssetDesign/Char/Player/Feina/BP_Feina_Summon.44"
      },
      "MonMoveComponent": {
        "ObjectName": "MonMoveLogicComponent'Default__BP_Feina_Summon_C:MonMoveLogicComponent'",
        "ObjectPath": "EM/Content/AssetDesign/Char/Player/Feina/BP_Feina_Summon.43"
      },
      "SignificanceComponent": {
        "ObjectName": "AISignificanceComponent'Default__BP_Feina_Summon_C:SignificanceComponent'",
        "ObjectPath": "EM/Content/AssetDesign/Char/Player/Feina/BP_Feina_Summon.22"
      },
      "BudgetAllocComponent": {
        "ObjectName": "AIBudgetAllocateComponent'Default__BP_Feina_Summon_C:BudgetAllocComponent'",
        "ObjectPath": "EM/Content/AssetDesign/Char/Player/Feina/BP_Feina_Summon.20"
      },
      "CharRenderBoxComponent": {
        "ObjectName": "CharRenderBoxComponent'Default__BP_Feina_Summon_C:CharRenderBoxComponent'",
        "ObjectPath": "EM/Content/AssetDesign/Char/Player/Feina/BP_Feina_Summon.33"
      },
      "MonRotateProcessComponent": {
        "ObjectName": "MonRotateProcessComponent'Default__BP_Feina_Summon_C:MonRotateProcessComponent'",
        "ObjectPath": "EM/Content/AssetDesign/Char/Player/Feina/BP_Feina_Summon.45"
      },
      "JumpWordComponent": {
        "ObjectName": "BP_JumpWordComponent_C'Default__BP_Feina_Summon_C:BP_JumpWordComponent'",
        "ObjectPath": "EM/Content/AssetDesign/Char/Player/Feina/BP_Feina_Summon.28"
      },
      "CharacterFashion": {
        "ObjectName": "BP_CharacterFashion_C'Default__BP_Feina_Summon_C:BP_CharacterFashion'",
        "ObjectPath": "EM/Content/AssetDesign/Char/Player/Feina/BP_Feina_Summon.25"
      },
      "BattleEvent": {
        "ObjectName": "BP_BattleEventComponent_C'Default__BP_Feina_Summon_C:BP_BattleEventComponent'",
        "ObjectPath": "EM/Content/AssetDesign/Char/Player/Feina/BP_Feina_Summon.23"
      },
      "BuffManager": {
        "ObjectName": "BP_BuffManager_C'Default__BP_Feina_Summon_C:BP_BuffManager'",
        "ObjectPath": "EM/Content/AssetDesign/Char/Player/Feina/BP_Feina_Summon.24"
      },
      "FXComponent": {
        "ObjectName": "BP_FXComponent_C'Default__BP_Feina_Summon_C:BP_FXComponent'",
        "ObjectPath": "EM/Content/AssetDesign/Char/Player/Feina/BP_Feina_Summon.26"
      },
      "HollowSphereComponent": {
        "ObjectName": "BP_HollowSphereComponent_C'Default__BP_Feina_Summon_C:BP_HollowSphereComponent'",
        "ObjectPath": "EM/Content/AssetDesign/Char/Player/Feina/BP_Feina_Summon.27"
      },
      "SkillsComponent": {
        "ObjectName": "BP_SkillsComponent_C'Default__BP_Feina_Summon_C:BP_SkillsComponent'",
        "ObjectPath": "EM/Content/AssetDesign/Char/Player/Feina/BP_Feina_Summon.29"
      },
      "CharFSMComp": {
        "ObjectName": "CharacterFSM'Default__BP_Feina_Summon_C:CharFSMComp'",
        "ObjectPath": "EM/Content/AssetDesign/Char/Player/Feina/BP_Feina_Summon.32"
      },
      "AutoSyncProp": {
        "ObjectName": "CharacterAutoSyncProp'Default__BP_Feina_Summon_C:AutoSyncProp'",
        "ObjectPath": "EM/Content/AssetDesign/Char/Player/Feina/BP_Feina_Summon.31"
      },
      "MotionWarpingComponent": {
        "ObjectName": "MotionWarpingComponent'Default__BP_Feina_Summon_C:MotionWarpingComponent'",
        "ObjectPath": "EM/Content/AssetDesign/Char/Player/Feina/BP_Feina_Summon.48"
      },
      "EMComponents": [
        {
          "Key": "CharFSMComp",
          "Value": {
            "ObjectName": "CharacterFSM'Default__BP_Feina_Summon_C:CharFSMComp'",
            "ObjectPath": "EM/Content/AssetDesign/Char/Player/Feina/BP_Feina_Summon.32"
          }
        }
      ],
      "MoveRequestComponent": {
        "ObjectName": "MoveRequestComponent'Default__BP_Feina_Summon_C:MoveRequestComponent'",
        "ObjectPath": "EM/Content/AssetDesign/Char/Player/Feina/BP_Feina_Summon.49"
      },
      "Mesh": {
        "ObjectName": "MonSkeletalMeshComponent'Default__BP_Feina_Summon_C:CharacterMesh0'",
        "ObjectPath": "EM/Content/AssetDesign/Char/Player/Feina/BP_Feina_Summon.46"
      },
      "CharacterMovement": {
        "ObjectName": "MonCharMoveComp'Default__BP_Feina_Summon_C:CharMoveComp'",
        "ObjectPath": "EM/Content/AssetDesign/Char/Player/Feina/BP_Feina_Summon.39"
      },
      "CapsuleComponent": {
        "ObjectName": "EMCapsuleComponent'Default__BP_Feina_Summon_C:CollisionCylinder'",
        "ObjectPath": "EM/Content/AssetDesign/Char/Player/Feina/BP_Feina_Summon.35"
      },
      "RootComponent": {
        "ObjectName": "EMCapsuleComponent'Default__BP_Feina_Summon_C:CollisionCylinder'",
        "ObjectPath": "EM/Content/AssetDesign/Char/Player/Feina/BP_Feina_Summon.35"
      }
    }
  },
  {
    "Type": "AIBudgetAllocateComponent",
    "Name": "BudgetAllocComponent",
    "Outer": "Default__BP_Feina_Summon_C",
    "Class": "UScriptClass'AIBudgetAllocateComponent'",
    "Template": {
      "ObjectName": "AIBudgetAllocateComponent'Default__BP_MonsterCharacter_C:BudgetAllocComponent'",
      "ObjectPath": "EM/Content/BluePrints/Char/BP_Monsters/BP_MonsterCharacter.44"
    },
    "Flags": "RF_Public | RF_Transactional | RF_ArchetypeObject | RF_DefaultSubObject | RF_WasLoaded | RF_LoadCompleted"
  },
  {
    "Type": "AirWallPenetrateComponent",
    "Name": "AirWallPenetrateComponent",
    "Outer": "Default__BP_Feina_Summon_C",
    "Class": "UScriptClass'AirWallPenetrateComponent'",
    "Template": {
      "ObjectName": "AirWallPenetrateComponent'Default__BP_MonsterCharacter_C:AirWallPenetrateComponent'",
      "ObjectPath": "EM/Content/BluePrints/Char/BP_Monsters/BP_MonsterCharacter.45"
    },
    "Flags": "RF_Public | RF_Transactional | RF_ArchetypeObject | RF_DefaultSubObject | RF_WasLoaded | RF_LoadCompleted"
  },
  {
    "Type": "AISignificanceComponent",
    "Name": "SignificanceComponent",
    "Outer": "Default__BP_Feina_Summon_C",
    "Class": "UScriptClass'AISignificanceComponent'",
    "Template": {
      "ObjectName": "AISignificanceComponent'Default__BP_MonsterCharacter_C:SignificanceComponent'",
      "ObjectPath": "EM/Content/BluePrints/Char/BP_Monsters/BP_MonsterCharacter.46"
    },
    "Flags": "RF_Public | RF_Transactional | RF_ArchetypeObject | RF_DefaultSubObject | RF_WasLoaded | RF_LoadCompleted"
  },
  {
    "Type": "BP_BattleEventComponent_C",
    "Name": "BP_BattleEventComponent",
    "Outer": "Default__BP_Feina_Summon_C",
    "Class": "BlueprintGeneratedClass'EM/Content/BluePrints/Combat/BP_BattleEventComponent.BP_BattleEventComponent_C'",
    "Template": {
      "ObjectName": "BP_BattleEventComponent_C'Default__BP_MonsterCharacter_C:BP_BattleEventComponent'",
      "ObjectPath": "EM/Content/BluePrints/Char/BP_Monsters/BP_MonsterCharacter.48"
    },
    "Flags": "RF_Public | RF_Transactional | RF_ArchetypeObject | RF_DefaultSubObject | RF_WasLoaded | RF_LoadCompleted"
  },
  {
    "Type": "BP_BuffManager_C",
    "Name": "BP_BuffManager",
    "Outer": "Default__BP_Feina_Summon_C",
    "Class": "BlueprintGeneratedClass'EM/Content/BluePrints/Combat/Buff/BP_BuffManager.BP_BuffManager_C'",
    "Template": {
      "ObjectName": "BP_BuffManager_C'Default__BP_MonsterCharacter_C:BP_BuffManager'",
      "ObjectPath": "EM/Content/BluePrints/Char/BP_Monsters/BP_MonsterCharacter.49"
    },
    "Flags": "RF_Public | RF_Transactional | RF_ArchetypeObject | RF_DefaultSubObject | RF_WasLoaded | RF_LoadCompleted"
  },
  {
    "Type": "BP_CharacterFashion_C",
    "Name": "BP_CharacterFashion",
    "Outer": "Default__BP_Feina_Summon_C",
    "Class": "BlueprintGeneratedClass'EM/Content/BluePrints/Char/BP_CharacterFashion.BP_CharacterFashion_C'",
    "Template": {
      "ObjectName": "BP_CharacterFashion_C'Default__BP_MonsterCharacter_C:BP_CharacterFashion'",
      "ObjectPath": "EM/Content/BluePrints/Char/BP_Monsters/BP_MonsterCharacter.50"
    },
    "Flags": "RF_Public | RF_Transactional | RF_ArchetypeObject | RF_DefaultSubObject | RF_WasLoaded | RF_LoadCompleted"
  },
  {
    "Type": "BP_FXComponent_C",
    "Name": "BP_FXComponent",
    "Outer": "Default__BP_Feina_Summon_C",
    "Class": "BlueprintGeneratedClass'EM/Content/BluePrints/Char/BP_FXComponent.BP_FXComponent_C'",
    "Template": {
      "ObjectName": "BP_FXComponent_C'Default__BP_MonsterCharacter_C:BP_FXComponent'",
      "ObjectPath": "EM/Content/BluePrints/Char/BP_Monsters/BP_MonsterCharacter.51"
    },
    "Flags": "RF_Public | RF_Transactional | RF_ArchetypeObject | RF_DefaultSubObject | RF_WasLoaded | RF_LoadCompleted"
  },
  {
    "Type": "BP_HollowSphereComponent_C",
    "Name": "BP_HollowSphereComponent",
    "Outer": "Default__BP_Feina_Summon_C",
    "Class": "BlueprintGeneratedClass'EM/Content/BluePrints/Combat/BP_HollowSphereComponent.BP_HollowSphereComponent_C'",
    "Template": {
      "ObjectName": "BP_HollowSphereComponent_C'Default__BP_MonsterCharacter_C:BP_HollowSphereComponent'",
      "ObjectPath": "EM/Content/BluePrints/Char/BP_Monsters/BP_MonsterCharacter.52"
    },
    "Flags": "RF_Public | RF_Transactional | RF_ArchetypeObject | RF_DefaultSubObject | RF_WasLoaded | RF_LoadCompleted",
    "Properties": {
      "OnComponentBeginOverlap": {
        "InvocationList": [
          {
            "Object": {
              "ObjectName": "BP_HollowSphereComponent_C'Default__BP_Feina_Summon_C:BP_HollowSphereComponent'",
              "ObjectPath": "EM/Content/AssetDesign/Char/Player/Feina/BP_Feina_Summon.27"
            },
            "FunctionName": "OnBeginOverlap"
          }
        ]
      },
      "OnComponentEndOverlap": {
        "InvocationList": [
          {
            "Object": {
              "ObjectName": "BP_HollowSphereComponent_C'Default__BP_Feina_Summon_C:BP_HollowSphereComponent'",
              "ObjectPath": "EM/Content/AssetDesign/Char/Player/Feina/BP_Feina_Summon.27"
            },
            "FunctionName": "OnEndOverlap"
          }
        ]
      },
      "AttachParent": {
        "ObjectName": "EMCapsuleComponent'Default__BP_Feina_Summon_C:CollisionCylinder'",
        "ObjectPath": "EM/Content/AssetDesign/Char/Player/Feina/BP_Feina_Summon.35"
      }
    }
  },
  {
    "Type": "BP_JumpWordComponent_C",
    "Name": "BP_JumpWordComponent",
    "Outer": "Default__BP_Feina_Summon_C",
    "Class": "BlueprintGeneratedClass'EM/Content/BluePrints/Char/BP_JumpWordComponent.BP_JumpWordComponent_C'",
    "Template": {
      "ObjectName": "BP_JumpWordComponent_C'Default__BP_MonsterCharacter_C:BP_JumpWordComponent'",
      "ObjectPath": "EM/Content/BluePrints/Char/BP_Monsters/BP_MonsterCharacter.53"
    },
    "Flags": "RF_Public | RF_Transactional | RF_ArchetypeObject | RF_DefaultSubObject | RF_WasLoaded | RF_LoadCompleted"
  },
  {
    "Type": "BP_SkillsComponent_C",
    "Name": "BP_SkillsComponent",
    "Outer": "Default__BP_Feina_Summon_C",
    "Class": "BlueprintGeneratedClass'EM/Content/BluePrints/Combat/Skill/BP_SkillsComponent.BP_SkillsComponent_C'",
    "Template": {
      "ObjectName": "BP_SkillsComponent_C'Default__BP_MonsterCharacter_C:BP_SkillsComponent'",
      "ObjectPath": "EM/Content/BluePrints/Char/BP_Monsters/BP_MonsterCharacter.54"
    },
    "Flags": "RF_Public | RF_Transactional | RF_ArchetypeObject | RF_DefaultSubObject | RF_WasLoaded | RF_LoadCompleted"
  },
  {
    "Type": "CapsuleComponent",
    "Name": "MonsterHitedCapsule_GEN_VARIABLE",
    "Outer": "BP_Feina_Summon_C",
    "Class": "UScriptClass'CapsuleComponent'",
    "Template": {
      "ObjectName": "CapsuleComponent'BP_MonsterCharacter_C:MonsterHitedCapsule_GEN_VARIABLE'",
      "ObjectPath": "EM/Content/BluePrints/Char/BP_Monsters/BP_MonsterCharacter.55"
    },
    "Flags": "RF_Public | RF_Transactional | RF_ArchetypeObject | RF_WasLoaded | RF_LoadCompleted | RF_InheritableComponentTemplate",
    "Properties": {
      "BodyInstance": {
        "ObjectType": "ECC_WorldStatic",
        "CollisionEnabled": "ECollisionEnabled::NoCollision",
        "CollisionProfileName": "NoCollision",
        "CollisionResponses": {
          "ResponseArray": [
            {
              "Channel": "Visibility",
              "Response": "ECR_Ignore"
            },
            {
              "Channel": "Camera",
              "Response": "ECR_Ignore"
            },
            {
              "Channel": "TraceExceptChar",
              "Response": "ECR_Ignore"
            }
          ]
        }
      }
    }
  },
  {
    "Type": "CharacterAutoSyncProp",
    "Name": "AutoSyncProp",
    "Outer": "Default__BP_Feina_Summon_C",
    "Class": "UScriptClass'CharacterAutoSyncProp'",
    "Template": {
      "ObjectName": "CharacterAutoSyncProp'Default__BP_MonsterCharacter_C:AutoSyncProp'",
      "ObjectPath": "EM/Content/BluePrints/Char/BP_Monsters/BP_MonsterCharacter.56"
    },
    "Flags": "RF_Public | RF_Transactional | RF_ArchetypeObject | RF_DefaultSubObject | RF_WasLoaded | RF_LoadCompleted"
  },
  {
    "Type": "CharacterFSM",
    "Name": "CharFSMComp",
    "Outer": "Default__BP_Feina_Summon_C",
    "Class": "UScriptClass'CharacterFSM'",
    "Template": {
      "ObjectName": "CharacterFSM'Default__BP_MonsterCharacter_C:CharFSMComp'",
      "ObjectPath": "EM/Content/BluePrints/Char/BP_Monsters/BP_MonsterCharacter.57"
    },
    "Flags": "RF_Public | RF_Transactional | RF_ArchetypeObject | RF_DefaultSubObject | RF_WasLoaded | RF_LoadCompleted"
  },
  {
    "Type": "CharRenderBoxComponent",
    "Name": "CharRenderBoxComponent",
    "Outer": "Default__BP_Feina_Summon_C",
    "Class": "UScriptClass'CharRenderBoxComponent'",
    "Template": {
      "ObjectName": "CharRenderBoxComponent'Default__BP_MonsterCharacter_C:CharRenderBoxComponent'",
      "ObjectPath": "EM/Content/BluePrints/Char/BP_Monsters/BP_MonsterCharacter.58"
    },
    "Flags": "RF_Public | RF_Transactional | RF_ArchetypeObject | RF_DefaultSubObject | RF_WasLoaded | RF_LoadCompleted",
    "Properties": {
      "AttachParent": {
        "ObjectName": "EMCapsuleComponent'Default__BP_Feina_Summon_C:CollisionCylinder'",
        "ObjectPath": "EM/Content/AssetDesign/Char/Player/Feina/BP_Feina_Summon.35"
      }
    }
  },
  {
    "Type": "DestructableBodyMgr",
    "Name": "DestructableBodyMgr",
    "Outer": "Default__BP_Feina_Summon_C",
    "Class": "UScriptClass'DestructableBodyMgr'",
    "Template": {
      "ObjectName": "DestructableBodyMgr'Default__BP_MonsterCharacter_C:DestructableBodyMgr'",
      "ObjectPath": "EM/Content/BluePrints/Char/BP_Monsters/BP_MonsterCharacter.63"
    },
    "Flags": "RF_Public | RF_Transactional | RF_ArchetypeObject | RF_DefaultSubObject | RF_WasLoaded | RF_LoadCompleted"
  },
  {
    "Type": "EMCapsuleComponent",
    "Name": "CollisionCylinder",
    "Outer": "Default__BP_Feina_Summon_C",
    "Class": "UScriptClass'EMCapsuleComponent'",
    "Template": {
      "ObjectName": "EMCapsuleComponent'Default__BP_MonsterCharacter_C:CollisionCylinder'",
      "ObjectPath": "EM/Content/BluePrints/Char/BP_Monsters/BP_MonsterCharacter.64"
    },
    "Flags": "RF_Public | RF_Transactional | RF_ArchetypeObject | RF_DefaultSubObject | RF_WasLoaded | RF_LoadCompleted",
    "Properties": {
      "CapsuleHalfHeight": 80.0,
      "bGenerateOverlapEvents": false,
      "BodyInstance": {
        "ObjectType": "ECC_WorldStatic",
        "CollisionEnabled": "ECollisionEnabled::NoCollision",
        "CollisionProfileName": "NoCollision",
        "CollisionResponses": {
          "ResponseArray": [
            {
              "Channel": "Visibility",
              "Response": "ECR_Ignore"
            },
            {
              "Channel": "Camera",
              "Response": "ECR_Ignore"
            },
            {
              "Channel": "TraceExceptChar",
              "Response": "ECR_Ignore"
            }
          ]
        }
      }
    }
  },
  {
    "Type": "EQSTestingComponent",
    "Name": "EQSTestingComponent",
    "Outer": "Default__BP_Feina_Summon_C",
    "Class": "UScriptClass'EQSTestingComponent'",
    "Template": {
      "ObjectName": "EQSTestingComponent'Default__BP_MonsterCharacter_C:EQSTestingComponent'",
      "ObjectPath": "EM/Content/BluePrints/Char/BP_Monsters/BP_MonsterCharacter.65"
    },
    "Flags": "RF_Public | RF_Transactional | RF_ArchetypeObject | RF_DefaultSubObject | RF_WasLoaded | RF_LoadCompleted"
  },
  {
    "Type": "InheritableComponentHandler",
    "Name": "InheritableComponentHandler",
    "Outer": "BP_Feina_Summon_C",
    "Class": "UScriptClass'InheritableComponentHandler'",
    "Flags": "RF_WasLoaded | RF_LoadCompleted",
    "Properties": {
      "Records": [
        {
          "ComponentClass": {
            "ObjectName": "Class'CapsuleComponent'",
            "ObjectPath": "/Script/Engine"
          },
          "ComponentTemplate": {
            "ObjectName": "CapsuleComponent'BP_Feina_Summon_C:MonsterHitedCapsule_GEN_VARIABLE'",
            "ObjectPath": "EM/Content/AssetDesign/Char/Player/Feina/BP_Feina_Summon.30"
          },
          "ComponentKey": {
            "OwnerClass": {
              "ObjectName": "BlueprintGeneratedClass'BP_MonsterCharacter_C'",
              "ObjectPath": "EM/Content/BluePrints/Char/BP_Monsters/BP_MonsterCharacter.42"
            },
            "SCSVariableName": "MonsterHitedCapsule",
            "AssociatedGuid": "82515071-4AD83C57-03F585B4-956A778C"
          },
          "CookedComponentInstancingData": {
            "ChangedPropertyList": [],
            "bHasValidCookedData": false
          }
        }
      ]
    }
  },
  {
    "Type": "MonAlertComponent",
    "Name": "MonAlertComponent",
    "Outer": "Default__BP_Feina_Summon_C",
    "Class": "UScriptClass'MonAlertComponent'",
    "Template": {
      "ObjectName": "MonAlertComponent'Default__BP_MonsterCharacter_C:MonAlertComponent'",
      "ObjectPath": "EM/Content/BluePrints/Char/BP_Monsters/BP_MonsterCharacter.66"
    },
    "Flags": "RF_Public | RF_Transactional | RF_ArchetypeObject | RF_DefaultSubObject | RF_WasLoaded | RF_LoadCompleted"
  },
  {
    "Type": "MonCharMoveComp",
    "Name": "CharMoveComp",
    "Outer": "Default__BP_Feina_Summon_C",
    "Class": "UScriptClass'MonCharMoveComp'",
    "Template": {
      "ObjectName": "MonCharMoveComp'Default__BP_MonsterCharacter_C:CharMoveComp'",
      "ObjectPath": "EM/Content/BluePrints/Char/BP_Monsters/BP_MonsterCharacter.67"
    },
    "Flags": "RF_Public | RF_Transactional | RF_ArchetypeObject | RF_DefaultSubObject | RF_WasLoaded | RF_LoadCompleted"
  },
  {
    "Type": "MonDecisionStateComponent",
    "Name": "MonDecisionStateComponent",
    "Outer": "Default__BP_Feina_Summon_C",
    "Class": "UScriptClass'MonDecisionStateComponent'",
    "Template": {
      "ObjectName": "MonDecisionStateComponent'Default__BP_MonsterCharacter_C:MonDecisionStateComponent'",
      "ObjectPath": "EM/Content/BluePrints/Char/BP_Monsters/BP_MonsterCharacter.68"
    },
    "Flags": "RF_Public | RF_Transactional | RF_ArchetypeObject | RF_DefaultSubObject | RF_WasLoaded | RF_LoadCompleted"
  },
  {
    "Type": "MonEliteComponent",
    "Name": "MonEliteComponent",
    "Outer": "Default__BP_Feina_Summon_C",
    "Class": "UScriptClass'MonEliteComponent'",
    "Template": {
      "ObjectName": "MonEliteComponent'Default__BP_MonsterCharacter_C:MonEliteComponent'",
      "ObjectPath": "EM/Content/BluePrints/Char/BP_Monsters/BP_MonsterCharacter.69"
    },
    "Flags": "RF_Public | RF_Transactional | RF_ArchetypeObject | RF_DefaultSubObject | RF_WasLoaded | RF_LoadCompleted"
  },
  {
    "Type": "MonExtraVitaminComponent",
    "Name": "MonExtraVitaminComponent",
    "Outer": "Default__BP_Feina_Summon_C",
    "Class": "UScriptClass'MonExtraVitaminComponent'",
    "Template": {
      "ObjectName": "MonExtraVitaminComponent'Default__BP_MonsterCharacter_C:MonExtraVitaminComponent'",
      "ObjectPath": "EM/Content/BluePrints/Char/BP_Monsters/BP_MonsterCharacter.70"
    },
    "Flags": "RF_Public | RF_Transactional | RF_ArchetypeObject | RF_DefaultSubObject | RF_WasLoaded | RF_LoadCompleted"
  },
  {
    "Type": "MonMoveLogicComponent",
    "Name": "MonMoveLogicComponent",
    "Outer": "Default__BP_Feina_Summon_C",
    "Class": "UScriptClass'MonMoveLogicComponent'",
    "Template": {
      "ObjectName": "MonMoveLogicComponent'Default__BP_MonsterCharacter_C:MonMoveLogicComponent'",
      "ObjectPath": "EM/Content/BluePrints/Char/BP_Monsters/BP_MonsterCharacter.71"
    },
    "Flags": "RF_Public | RF_Transactional | RF_ArchetypeObject | RF_DefaultSubObject | RF_WasLoaded | RF_LoadCompleted"
  },
  {
    "Type": "MonOptimizationComponent",
    "Name": "MonOptimizationComponent",
    "Outer": "Default__BP_Feina_Summon_C",
    "Class": "UScriptClass'MonOptimizationComponent'",
    "Template": {
      "ObjectName": "MonOptimizationComponent'Default__BP_MonsterCharacter_C:MonOptimizationComponent'",
      "ObjectPath": "EM/Content/BluePrints/Char/BP_Monsters/BP_MonsterCharacter.72"
    },
    "Flags": "RF_Public | RF_Transactional | RF_ArchetypeObject | RF_DefaultSubObject | RF_WasLoaded | RF_LoadCompleted"
  },
  {
    "Type": "MonRotateProcessComponent",
    "Name": "MonRotateProcessComponent",
    "Outer": "Default__BP_Feina_Summon_C",
    "Class": "UScriptClass'MonRotateProcessComponent'",
    "Template": {
      "ObjectName": "MonRotateProcessComponent'Default__BP_MonsterCharacter_C:MonRotateProcessComponent'",
      "ObjectPath": "EM/Content/BluePrints/Char/BP_Monsters/BP_MonsterCharacter.73"
    },
    "Flags": "RF_Public | RF_Transactional | RF_ArchetypeObject | RF_DefaultSubObject | RF_WasLoaded | RF_LoadCompleted"
  },
  {
    "Type": "MonSkeletalMeshComponent",
    "Name": "CharacterMesh0",
    "Outer": "Default__BP_Feina_Summon_C",
    "Class": "UScriptClass'MonSkeletalMeshComponent'",
    "Template": {
      "ObjectName": "MonSkeletalMeshComponent'Default__BP_MonsterCharacter_C:CharacterMesh0'",
      "ObjectPath": "EM/Content/BluePrints/Char/BP_Monsters/BP_MonsterCharacter.74"
    },
    "Flags": "RF_Public | RF_Transactional | RF_ArchetypeObject | RF_DefaultSubObject | RF_WasLoaded | RF_LoadCompleted",
    "Properties": {
      "AnimationMode": "EAnimationMode::AnimationSingleNode",
      "OnAnimInitialized": {
        "InvocationList": [
          {
            "Object": {
              "ObjectName": "BP_Feina_Summon_C'Default__BP_Feina_Summon_C'",
              "ObjectPath": "EM/Content/AssetDesign/Char/Player/Feina/BP_Feina_Summon.19"
            },
            "FunctionName": "OnAnimInitialized"
          }
        ]
      },
      "SkeletalMesh": {
        "ObjectName": "SkeletalMesh'Feina_Sum01_SM'",
        "ObjectPath": "EM/Content/Asset/Char/Player/Char019_Feina/Mesh/Feina_Sum01_SM.0"
      },
      "AttachParent": {
        "ObjectName": "EMCapsuleComponent'Default__BP_Feina_Summon_C:CollisionCylinder'",
        "ObjectPath": "EM/Content/AssetDesign/Char/Player/Feina/BP_Feina_Summon.35"
      },
      "RelativeLocation": {
        "X": 0.0,
        "Y": 0.0,
        "Z": -80.0
      },
      "RelativeRotation": {
        "Pitch": 0.0,
        "Yaw": 0.0,
        "Roll": 0.0
      },
      "bVisible": false
    }
  },
  {
    "Type": "MonUpdateBBComponent",
    "Name": "MonUpdateBBComponent",
    "Outer": "Default__BP_Feina_Summon_C",
    "Class": "UScriptClass'MonUpdateBBComponent'",
    "Template": {
      "ObjectName": "MonUpdateBBComponent'Default__BP_MonsterCharacter_C:MonUpdateBBComponent'",
      "ObjectPath": "EM/Content/BluePrints/Char/BP_Monsters/BP_MonsterCharacter.76"
    },
    "Flags": "RF_Public | RF_Transactional | RF_ArchetypeObject | RF_DefaultSubObject | RF_WasLoaded | RF_LoadCompleted"
  },
  {
    "Type": "MotionWarpingComponent",
    "Name": "MotionWarpingComponent",
    "Outer": "Default__BP_Feina_Summon_C",
    "Class": "UScriptClass'MotionWarpingComponent'",
    "Template": {
      "ObjectName": "MotionWarpingComponent'Default__BP_MonsterCharacter_C:MotionWarpingComponent'",
      "ObjectPath": "EM/Content/BluePrints/Char/BP_Monsters/BP_MonsterCharacter.77"
    },
    "Flags": "RF_Public | RF_Transactional | RF_ArchetypeObject | RF_DefaultSubObject | RF_WasLoaded | RF_LoadCompleted"
  },
  {
    "Type": "MoveRequestComponent",
    "Name": "MoveRequestComponent",
    "Outer": "Default__BP_Feina_Summon_C",
    "Class": "UScriptClass'MoveRequestComponent'",
    "Template": {
      "ObjectName": "MoveRequestComponent'Default__BP_MonsterCharacter_C:MoveRequestComponent'",
      "ObjectPath": "EM/Content/BluePrints/Char/BP_Monsters/BP_MonsterCharacter.78"
    },
    "Flags": "RF_Public | RF_Transactional | RF_ArchetypeObject | RF_DefaultSubObject | RF_WasLoaded | RF_LoadCompleted"
  },
  {
    "Type": "NavLinkJumpComponent",
    "Name": "NavLinkJumpComponent",
    "Outer": "Default__BP_Feina_Summon_C",
    "Class": "UScriptClass'NavLinkJumpComponent'",
    "Template": {
      "ObjectName": "NavLinkJumpComponent'Default__BP_MonsterCharacter_C:NavLinkJumpComponent'",
      "ObjectPath": "EM/Content/BluePrints/Char/BP_Monsters/BP_MonsterCharacter.79"
    },
    "Flags": "RF_Public | RF_Transactional | RF_ArchetypeObject | RF_DefaultSubObject | RF_WasLoaded | RF_LoadCompleted"
  },
  {
    "Type": "SceneComponent",
    "Name": "DefaultSceneRoot_GEN_VARIABLE",
    "Outer": "BP_Feina_Summon_C",
    "Class": "UScriptClass'SceneComponent'",
    "Flags": "RF_Public | RF_Transactional | RF_ArchetypeObject | RF_WasLoaded | RF_LoadCompleted"
  },
  {
    "Type": "SCS_Node",
    "Name": "SCS_Node_0",
    "Outer": "SimpleConstructionScript_0",
    "Class": "UScriptClass'SCS_Node'",
    "Flags": "RF_Transactional | RF_WasLoaded | RF_LoadCompleted",
    "Properties": {
      "ComponentClass": {
        "ObjectName": "Class'SceneComponent'",
        "ObjectPath": "/Script/Engine"
      },
      "ComponentTemplate": {
        "ObjectName": "SceneComponent'BP_Feina_Summon_C:DefaultSceneRoot_GEN_VARIABLE'",
        "ObjectPath": "EM/Content/AssetDesign/Char/Player/Feina/BP_Feina_Summon.51"
      },
      "VariableGuid": "C3AADB6B-419CC53F-2A52BD99-673E4A3A",
      "InternalVariableName": "DefaultSceneRoot"
    }
  },
  {
    "Type": "SimpleConstructionScript",
    "Name": "SimpleConstructionScript_0",
    "Outer": "BP_Feina_Summon_C",
    "Class": "UScriptClass'SimpleConstructionScript'",
    "Flags": "RF_Transactional | RF_WasLoaded | RF_LoadCompleted",
    "Properties": {
      "DefaultSceneRootNode": {
        "ObjectName": "SCS_Node'BP_Feina_Summon_C:SimpleConstructionScript_0.SCS_Node_0'",
        "ObjectPath": "EM/Content/AssetDesign/Char/Player/Feina/BP_Feina_Summon.52"
      }
    }
  },
  {
    "Type": "TimelineComponent",
    "Name": "BeAttackTimeline",
    "Outer": "Default__BP_Feina_Summon_C",
    "Class": "UScriptClass'TimelineComponent'",
    "Template": {
      "ObjectName": "TimelineComponent'Default__BP_MonsterCharacter_C:BeAttackTimeline'",
      "ObjectPath": "EM/Content/BluePrints/Char/BP_Monsters/BP_MonsterCharacter.89"
    },
    "Flags": "RF_Public | RF_Transactional | RF_ArchetypeObject | RF_DefaultSubObject | RF_WasLoaded | RF_LoadCompleted"
  }
]